<?xml version="1.0" encoding="utf-8"?>
<ode><userPreferences><userPreference><key>theme</key><value>base</value></userPreference></userPreferences><odeResources><odeResource><key>odeVersionId</key><value>20260322190753NWYAYY</value></odeResource><odeResource><key>odeId</key><value>20260322080845KIQKOR</value></odeResource><odeResource><key>odeVersionName</key><value>0</value></odeResource><odeResource><key>isDownload</key><value>true</value></odeResource><odeResource><key>eXeVersion</key><value>v3.0.2</value></odeResource></odeResources><odeProperties><odeProperty><key>pp_title</key><value>Mi barrio en 360º</value></odeProperty><odeProperty><key>pp_subtitle</key><value/></odeProperty><odeProperty><key>pp_lang</key><value>es</value></odeProperty><odeProperty><key>pp_author</key><value/></odeProperty><odeProperty><key>license</key><value>creative commons: attribution - share alike 4.0</value></odeProperty><odeProperty><key>pp_description</key><value/></odeProperty><odeProperty><key>exportSource</key><value>true</value></odeProperty><odeProperty><key>pp_addExeLink</key><value>true</value></odeProperty><odeProperty><key>pp_addPagination</key><value>false</value></odeProperty><odeProperty><key>pp_addSearchBox</key><value>false</value></odeProperty><odeProperty><key>pp_addAccessibilityToolbar</key><value>false</value></odeProperty><odeProperty><key>pp_extraHeadContent</key><value/></odeProperty><odeProperty><key>footer</key><value/></odeProperty></odeProperties><odeNavStructures><odeNavStructure><odePageId>20260322190753ENIYTU</odePageId><odeParentPageId/><pageName>Presentación del proyecto</pageName><odeNavStructureOrder>1</odeNavStructureOrder><odeNavStructureProperties><odeNavStructureProperty><key>titleNode</key><value>Presentación del proyecto</value></odeNavStructureProperty><odeNavStructureProperty><key>hidePageTitle</key><value>false</value></odeNavStructureProperty><odeNavStructureProperty><key>titleHtml</key><value/></odeNavStructureProperty><odeNavStructureProperty><key>editableInPage</key><value>false</value></odeNavStructureProperty><odeNavStructureProperty><key>titlePage</key><value>Presentación del proyecto</value></odeNavStructureProperty><odeNavStructureProperty><key>visibility</key><value>false</value></odeNavStructureProperty><odeNavStructureProperty><key>highlight</key><value>false</value></odeNavStructureProperty><odeNavStructureProperty><key>description</key><value/></odeNavStructureProperty></odeNavStructureProperties><odePagStructures><odePagStructure><odePageId>20260322190753ENIYTU</odePageId><odeBlockId>20260322190753CFIAZW</odeBlockId><blockName>Mi barrio en 360º</blockName><iconName>case</iconName><odePagStructureOrder>1</odePagStructureOrder><odePagStructureProperties><odePagStructureProperty><key>visibility</key><value>true</value></odePagStructureProperty><odePagStructureProperty><key>teacherOnly</key><value>false</value></odePagStructureProperty><odePagStructureProperty><key>allowToggle</key><value>true</value></odePagStructureProperty><odePagStructureProperty><key>minimized</key><value>false</value></odePagStructureProperty><odePagStructureProperty><key>identifier</key><value/></odePagStructureProperty><odePagStructureProperty><key>cssClass</key><value/></odePagStructureProperty></odePagStructureProperties><odeComponents><odeComponent><odePageId>20260322190753ENIYTU</odePageId><odeBlockId>20260322190753CFIAZW</odeBlockId><odeIdeviceId>20260322091656725RMI</odeIdeviceId><odeIdeviceTypeName>text</odeIdeviceTypeName><htmlView>&lt;div class="exe-text-template"&gt;&lt;div class="textIdeviceContent"&gt;
            &lt;div class="exe-text-activity"&gt;
                &lt;div&gt;&lt;p style="text-align: center;"&gt;&lt;span style="font-size: 24pt; color: #3598db; font-family: georgia, palatino, serif;"&gt;&lt;strong&gt;Mi barrio en 360º: ¡Pequeños guías locales!&lt;/strong&gt;&lt;/span&gt;&lt;/p&gt;
&lt;p&gt;&lt;strong&gt;&lt;span style="font-family: georgia, palatino, serif; font-size: 14pt;"&gt;1. Elementos Curriculares y Organizativos&lt;/span&gt;&lt;/strong&gt;&lt;/p&gt;
&lt;ul&gt;
&lt;li&gt;&lt;span style="font-family: georgia, palatino, serif;"&gt;&lt;strong&gt;Centro de interés&lt;/strong&gt;: El conocimiento del entorno cercano (servicios, comercios y normas de convivencia) y el uso responsable de la imagen digital.&lt;/span&gt;&lt;/li&gt;
&lt;li&gt;&lt;span style="font-family: georgia, palatino, serif;"&gt;Nivel al que va dirigido: 2º de Educación Primaria.&amp;nbsp;&lt;/span&gt;&lt;/li&gt;
&lt;li&gt;&lt;span style="font-family: georgia, palatino, serif;"&gt;Temporalización aproximada: 8 sesiones (repartidas en 3 semanas).&lt;/span&gt;&lt;/li&gt;
&lt;li&gt;&lt;span style="font-family: georgia, palatino, serif;"&gt;Áreas implicadas: Conocimiento del Medio, Lengua Castellana y Educación Artística.&amp;nbsp;&lt;/span&gt;&lt;span style="font-family: georgia, palatino, serif;"&gt;&lt;/span&gt;&lt;/li&gt;
&lt;/ul&gt;
&lt;p&gt;&lt;span style="font-size: 14pt;"&gt;&lt;strong&gt;&lt;span style="font-family: georgia, palatino, serif;"&gt;2. Descripción General&lt;/span&gt;&lt;/strong&gt;&lt;/span&gt;&lt;/p&gt;
&lt;ul&gt;
&lt;li style="text-align: justify;"&gt;&lt;span style="font-family: georgia, palatino, serif;"&gt;El alumnado se convertirá en "reporteros" de su localidad. Realizaremos una salida al entorno para fotografiar los puntos clave (ayuntamiento, parque, biblioteca, comercios).&lt;/span&gt;&lt;/li&gt;
&lt;li style="text-align: justify;"&gt;&lt;span style="font-family: georgia, palatino, serif;"&gt;&lt;strong&gt;Producto Final&lt;/strong&gt;: Crearemos un &lt;strong&gt;Mapa Interactivo Digital d&lt;/strong&gt;el Barrio (usando Genially). Al pulsar en cada punto, se abrirá un dibujo del niño/a junto a un audio grabado por ellos mismos explicando por qué ese lugar es importante y cómo debemos cuidarlo.&lt;/span&gt;&lt;/li&gt;
&lt;/ul&gt;
&lt;p style="text-align: justify;"&gt;&lt;br&gt;&lt;/p&gt;&lt;p class="clearfix"&gt;&lt;/p&gt;&lt;/div&gt;
            &lt;/div&gt;&lt;/div&gt;&lt;/div&gt;</htmlView><jsonProperties>{"ideviceId":"20260322091656725RMI","textInfoDurationInput":"","textInfoDurationTextInput":"Duración","textInfoParticipantsInput":"","textInfoParticipantsTextInput":"Agrupamiento","textTextarea":"&lt;p style=\"text-align: center;\"&gt;&lt;span style=\"font-size: 24pt; color: #3598db; font-family: georgia, palatino, serif;\"&gt;&lt;strong&gt;Mi barrio en 360º: ¡Pequeños guías locales!&lt;/strong&gt;&lt;/span&gt;&lt;/p&gt;\n&lt;p&gt;&lt;strong&gt;&lt;span style=\"font-family: georgia, palatino, serif; font-size: 14pt;\"&gt;1. Elementos Curriculares y Organizativos&lt;/span&gt;&lt;/strong&gt;&lt;/p&gt;\n&lt;ul&gt;\n&lt;li&gt;&lt;span style=\"font-family: georgia, palatino, serif;\"&gt;&lt;strong&gt;Centro de interés&lt;/strong&gt;: El conocimiento del entorno cercano (servicios, comercios y normas de convivencia) y el uso responsable de la imagen digital.&lt;/span&gt;&lt;/li&gt;\n&lt;li&gt;&lt;span style=\"font-family: georgia, palatino, serif;\"&gt;Nivel al que va dirigido: 2º de Educación Primaria. &lt;/span&gt;&lt;/li&gt;\n&lt;li&gt;&lt;span style=\"font-family: georgia, palatino, serif;\"&gt;Temporalización aproximada: 8 sesiones (repartidas en 3 semanas).&lt;/span&gt;&lt;/li&gt;\n&lt;li&gt;&lt;span style=\"font-family: georgia, palatino, serif;\"&gt;Áreas implicadas: Conocimiento del Medio, Lengua Castellana y Educación Artística. &lt;/span&gt;&lt;span style=\"font-family: georgia, palatino, serif;\"&gt;&lt;/span&gt;&lt;/li&gt;\n&lt;/ul&gt;\n&lt;p&gt;&lt;span style=\"font-size: 14pt;\"&gt;&lt;strong&gt;&lt;span style=\"font-family: georgia, palatino, serif;\"&gt;2. Descripción General&lt;/span&gt;&lt;/strong&gt;&lt;/span&gt;&lt;/p&gt;\n&lt;ul&gt;\n&lt;li style=\"text-align: justify;\"&gt;&lt;span style=\"font-family: georgia, palatino, serif;\"&gt;El alumnado se convertirá en \"reporteros\" de su localidad. Realizaremos una salida al entorno para fotografiar los puntos clave (ayuntamiento, parque, biblioteca, comercios).&lt;/span&gt;&lt;/li&gt;\n&lt;li style=\"text-align: justify;\"&gt;&lt;span style=\"font-family: georgia, palatino, serif;\"&gt;&lt;strong&gt;Producto Final&lt;/strong&gt;: Crearemos un &lt;strong&gt;Mapa Interactivo Digital d&lt;/strong&gt;el Barrio (usando Genially). Al pulsar en cada punto, se abrirá un dibujo del niño/a junto a un audio grabado por ellos mismos explicando por qué ese lugar es importante y cómo debemos cuidarlo.&lt;/span&gt;&lt;/li&gt;\n&lt;/ul&gt;\n&lt;p style=\"text-align: justify;\"&gt;&lt;br /&gt;&lt;/p&gt;","textFeedbackInput":"Mostrar retroalimentación","textFeedbackTextarea":""}</jsonProperties><odeComponentsOrder>1</odeComponentsOrder><odeComponentsProperties><odeComponentsProperty><key>visibility</key><value>true</value></odeComponentsProperty><odeComponentsProperty><key>teacherOnly</key><value>false</value></odeComponentsProperty><odeComponentsProperty><key>identifier</key><value/></odeComponentsProperty><odeComponentsProperty><key>cssClass</key><value/></odeComponentsProperty></odeComponentsProperties></odeComponent></odeComponents></odePagStructure></odePagStructures></odeNavStructure><odeNavStructure><odePageId>20260322190753HEFRZE</odePageId><odeParentPageId>20260322190753ENIYTU</odeParentPageId><pageName>Nuestras fotos y seguridad </pageName><odeNavStructureOrder>1</odeNavStructureOrder><odeNavStructureProperties><odeNavStructureProperty><key>titleNode</key><value/></odeNavStructureProperty><odeNavStructureProperty><key>hidePageTitle</key><value>false</value></odeNavStructureProperty><odeNavStructureProperty><key>titleHtml</key><value/></odeNavStructureProperty><odeNavStructureProperty><key>editableInPage</key><value>false</value></odeNavStructureProperty><odeNavStructureProperty><key>titlePage</key><value>Nuestras fotos y seguridad </value></odeNavStructureProperty><odeNavStructureProperty><key>visibility</key><value>true</value></odeNavStructureProperty><odeNavStructureProperty><key>highlight</key><value>false</value></odeNavStructureProperty><odeNavStructureProperty><key>description</key><value/></odeNavStructureProperty></odeNavStructureProperties><odePagStructures><odePagStructure><odePageId>20260322190753HEFRZE</odePageId><odeBlockId>20260322190753GBCAVV</odeBlockId><blockName>Protección de datos&amp;nbsp;</blockName><iconName>gallery</iconName><odePagStructureOrder>1</odePagStructureOrder><odePagStructureProperties><odePagStructureProperty><key>visibility</key><value>true</value></odePagStructureProperty><odePagStructureProperty><key>teacherOnly</key><value>false</value></odePagStructureProperty><odePagStructureProperty><key>allowToggle</key><value>true</value></odePagStructureProperty><odePagStructureProperty><key>minimized</key><value>false</value></odePagStructureProperty><odePagStructureProperty><key>identifier</key><value/></odePagStructureProperty><odePagStructureProperty><key>cssClass</key><value/></odePagStructureProperty></odePagStructureProperties><odeComponents><odeComponent><odePageId>20260322190753HEFRZE</odePageId><odeBlockId>20260322190753GBCAVV</odeBlockId><odeIdeviceId>20260322154845550HI1</odeIdeviceId><odeIdeviceTypeName>text</odeIdeviceTypeName><htmlView>&lt;div class="exe-text-template"&gt;&lt;div class="textIdeviceContent"&gt;
            &lt;div class="exe-text-activity"&gt;
                &lt;div&gt;&lt;p&gt;&lt;/p&gt;
&lt;p&gt;&lt;/p&gt;
&lt;p&gt;&lt;/p&gt;
&lt;p style="text-align: right;"&gt;&lt;img src="{{context_path}}/20260322154845550HI1/Infografia_Tecnologia_Seguridad_Informatica_Software_Ordenador_Ilustrado_Azul.jpg" title="Protección de datos" width="800" height="2000" alt="Cartel normas de seguridad digital"&gt;&lt;span style="color: #000000; font-size: 8pt;"&gt;Imagen creada con Canva (Licencia Gratuita de Canva).&lt;/span&gt;&lt;/p&gt;
&lt;p style="text-align: justify;"&gt;&lt;span style="font-size: 14pt;"&gt;&lt;strong&gt;&lt;span style="font-family: georgia, palatino, serif;"&gt;¡Tu primera misión de Reportero!🕵️‍♂️&lt;/span&gt;&lt;/strong&gt;&lt;/span&gt;&lt;/p&gt;
&lt;p style="text-align: justify;"&gt;&lt;span style="font-family: georgia, palatino, serif;"&gt;Antes de salir a la calle con la tablet o la cámara, lee estas preguntas con tu pareja de trabajo:&lt;/span&gt;&lt;/p&gt;
&lt;ul&gt;
&lt;li style="text-align: justify;"&gt;&lt;span style="font-family: georgia, palatino, serif;"&gt;¿Le hemos preguntado a esa persona si quiere salir en nuestra foto?&lt;/span&gt;&lt;/li&gt;
&lt;li style="text-align: justify;"&gt;&lt;span style="font-family: georgia, palatino, serif;"&gt;¿Estamos enseñando algo que sea secreto (como una matrícula o un nombre)?&lt;/span&gt;&lt;/li&gt;
&lt;li style="text-align: justify;"&gt;&lt;span style="font-family: georgia, palatino, serif;"&gt;¿Estamos cuidando a nuestro barrio mientras trabajamos?&lt;/span&gt;&lt;/li&gt;
&lt;/ul&gt;
&lt;p style="text-align: justify;"&gt;&lt;span style="font-family: georgia, palatino, serif;"&gt;¡Si la respuesta es SÍ a todo, ya podéis disparar vuestra cámara! 📸✨&lt;/span&gt;&lt;/p&gt;
&lt;p style="text-align: justify;"&gt;&lt;span style="color: #000000; font-size: 8pt;"&gt;&lt;/span&gt;&lt;/p&gt;&lt;p class="clearfix"&gt;&lt;/p&gt;&lt;/div&gt;
            &lt;/div&gt;&lt;/div&gt;&lt;/div&gt;</htmlView><jsonProperties>{"ideviceId":"20260322154845550HI1","textInfoDurationInput":"","textInfoDurationTextInput":"Duración","textInfoParticipantsInput":"","textInfoParticipantsTextInput":"Agrupamiento","textTextarea":"&lt;p&gt;&lt;/p&gt;\n&lt;p&gt;&lt;/p&gt;\n&lt;p&gt;&lt;/p&gt;\n&lt;p style=\"text-align: right;\"&gt;&lt;img src=\"{{context_path}}/20260322154845550HI1/Infografia_Tecnologia_Seguridad_Informatica_Software_Ordenador_Ilustrado_Azul.jpg\" title=\"Protección de datos\" width=\"800\" height=\"2000\" alt=\"Cartel normas de seguridad digital\" /&gt;&lt;span style=\"color: #000000; font-size: 8pt;\"&gt;Imagen creada con Canva (Licencia Gratuita de Canva).&lt;/span&gt;&lt;/p&gt;\n&lt;p style=\"text-align: justify;\"&gt;&lt;span style=\"font-size: 14pt;\"&gt;&lt;strong&gt;&lt;span style=\"font-family: georgia, palatino, serif;\"&gt;¡Tu primera misión de Reportero!🕵️‍♂️&lt;/span&gt;&lt;/strong&gt;&lt;/span&gt;&lt;/p&gt;\n&lt;p style=\"text-align: justify;\"&gt;&lt;span style=\"font-family: georgia, palatino, serif;\"&gt;Antes de salir a la calle con la tablet o la cámara, lee estas preguntas con tu pareja de trabajo:&lt;/span&gt;&lt;/p&gt;\n&lt;ul&gt;\n&lt;li style=\"text-align: justify;\"&gt;&lt;span style=\"font-family: georgia, palatino, serif;\"&gt;¿Le hemos preguntado a esa persona si quiere salir en nuestra foto?&lt;/span&gt;&lt;/li&gt;\n&lt;li style=\"text-align: justify;\"&gt;&lt;span style=\"font-family: georgia, palatino, serif;\"&gt;¿Estamos enseñando algo que sea secreto (como una matrícula o un nombre)?&lt;/span&gt;&lt;/li&gt;\n&lt;li style=\"text-align: justify;\"&gt;&lt;span style=\"font-family: georgia, palatino, serif;\"&gt;¿Estamos cuidando a nuestro barrio mientras trabajamos?&lt;/span&gt;&lt;/li&gt;\n&lt;/ul&gt;\n&lt;p style=\"text-align: justify;\"&gt;&lt;span style=\"font-family: georgia, palatino, serif;\"&gt;¡Si la respuesta es SÍ a todo, ya podéis disparar vuestra cámara! 📸✨&lt;/span&gt;&lt;/p&gt;\n&lt;p style=\"text-align: justify;\"&gt;&lt;span style=\"color: #000000; font-size: 8pt;\"&gt;&lt;/span&gt;&lt;/p&gt;","textFeedbackInput":"Mostrar retroalimentación","textFeedbackTextarea":""}</jsonProperties><odeComponentsOrder>1</odeComponentsOrder><odeComponentsProperties><odeComponentsProperty><key>visibility</key><value>true</value></odeComponentsProperty><odeComponentsProperty><key>teacherOnly</key><value>false</value></odeComponentsProperty><odeComponentsProperty><key>identifier</key><value/></odeComponentsProperty><odeComponentsProperty><key>cssClass</key><value/></odeComponentsProperty></odeComponentsProperties></odeComponent></odeComponents></odePagStructure></odePagStructures></odeNavStructure><odeNavStructure><odePageId>20260322190753DHLJKB</odePageId><odeParentPageId>20260322190753ENIYTU</odeParentPageId><pageName>Nuestra gran misión</pageName><odeNavStructureOrder>2</odeNavStructureOrder><odeNavStructureProperties><odeNavStructureProperty><key>titleNode</key><value/></odeNavStructureProperty><odeNavStructureProperty><key>hidePageTitle</key><value>false</value></odeNavStructureProperty><odeNavStructureProperty><key>titleHtml</key><value/></odeNavStructureProperty><odeNavStructureProperty><key>editableInPage</key><value>false</value></odeNavStructureProperty><odeNavStructureProperty><key>titlePage</key><value>Nuestra gran misión</value></odeNavStructureProperty><odeNavStructureProperty><key>visibility</key><value>true</value></odeNavStructureProperty><odeNavStructureProperty><key>highlight</key><value>false</value></odeNavStructureProperty><odeNavStructureProperty><key>description</key><value/></odeNavStructureProperty></odeNavStructureProperties><odePagStructures><odePagStructure><odePageId>20260322190753DHLJKB</odePageId><odeBlockId>20260322190753RMBVQS</odeBlockId><blockName>Nuestra gran misión: mapa del barrio&amp;nbsp;</blockName><iconName>explore</iconName><odePagStructureOrder>1</odePagStructureOrder><odePagStructureProperties><odePagStructureProperty><key>visibility</key><value>true</value></odePagStructureProperty><odePagStructureProperty><key>teacherOnly</key><value>false</value></odePagStructureProperty><odePagStructureProperty><key>allowToggle</key><value>true</value></odePagStructureProperty><odePagStructureProperty><key>minimized</key><value>false</value></odePagStructureProperty><odePagStructureProperty><key>identifier</key><value/></odePagStructureProperty><odePagStructureProperty><key>cssClass</key><value/></odePagStructureProperty></odePagStructureProperties><odeComponents><odeComponent><odePageId>20260322190753DHLJKB</odePageId><odeBlockId>20260322190753RMBVQS</odeBlockId><odeIdeviceId>2026032216323210011E</odeIdeviceId><odeIdeviceTypeName>text</odeIdeviceTypeName><htmlView>&lt;div class="exe-text-template"&gt;&lt;div class="textIdeviceContent"&gt;
            &lt;div class="exe-text-activity"&gt;
                &lt;div&gt;&lt;p style="text-align: center;"&gt;🗺️ &lt;span style="font-size: 14pt;"&gt;&lt;strong&gt;¡&lt;span style="font-family: georgia, palatino, serif;"&gt;Vamos a crear un Mapa Mágico!&lt;/span&gt;&lt;/strong&gt;&lt;/span&gt;&lt;/p&gt;
&lt;p&gt;&lt;span style="font-family: georgia, palatino, serif;"&gt;Chicos y chicas, nuestra misión es fabricar un Mapa Interactivo de nuestro barrio.&lt;/span&gt;&lt;/p&gt;
&lt;p&gt;&lt;span style="font-family: georgia, palatino, serif;"&gt;Pondremos vuestros dibujos de las tiendas y parques.&lt;/span&gt;&lt;br&gt;&lt;span style="font-family: georgia, palatino, serif;"&gt;Grabaremos vuestra voz contando secretos del barrio.&lt;/span&gt;&lt;br&gt;&lt;span style="font-family: georgia, palatino, serif;"&gt;¡Cualquier persona que pulse en el mapa podrá oírnos y vernos!&lt;/span&gt;&lt;br&gt;&lt;span style="font-family: georgia, palatino, serif;"&gt;Usaremos una herramienta genial llamada Genially. ¡Es muy fácil y divertida!&lt;/span&gt;&lt;/p&gt;
&lt;p&gt;&lt;span style="font-family: georgia, palatino, serif;"&gt;&lt;a href="https://view.genially.com/69b6cce63695ebf5939cb93b" title="Mapa del barrio" id="link_0"&gt;https://view.genially.com/69b6cce63695ebf5939cb93b&lt;/a&gt;&lt;/span&gt;&lt;/p&gt;
&lt;p&gt;&lt;span style="font-size: 8pt; font-family: georgia, palatino, serif;"&gt;Autoría: Araceli Servián/ Recurso creado con Genially / Licencia: Creative Commons BY-NC-SA 4.0&amp;nbsp;&lt;/span&gt;&lt;/p&gt;
&lt;p&gt;&lt;span style="font-size: 8pt; font-family: georgia, palatino, serif;"&gt;Imágen: Fuente: Consejería de Desarrollo Educativo y Formación Profesional (Junta de Andalucía). Licencia: CC BY-NC-SA (Reconocimiento-NoComercial-CompartirIgual).&lt;/span&gt;&lt;br&gt;&lt;span style="font-family: georgia, palatino, serif;"&gt;&amp;nbsp;&lt;/span&gt;&lt;/p&gt;&lt;p class="clearfix"&gt;&lt;/p&gt;&lt;/div&gt;
            &lt;/div&gt;&lt;/div&gt;&lt;/div&gt;</htmlView><jsonProperties>{"ideviceId":"2026032216323210011E","textInfoDurationInput":"","textInfoDurationTextInput":"Duración","textInfoParticipantsInput":"","textInfoParticipantsTextInput":"Agrupamiento","textTextarea":"&lt;p style=\"text-align: center;\"&gt;🗺️ &lt;span style=\"font-size: 14pt;\"&gt;&lt;strong&gt;¡&lt;span style=\"font-family: georgia, palatino, serif;\"&gt;Vamos a crear un Mapa Mágico!&lt;/span&gt;&lt;/strong&gt;&lt;/span&gt;&lt;/p&gt;\n&lt;p&gt;&lt;span style=\"font-family: georgia, palatino, serif;\"&gt;Chicos y chicas, nuestra misión es fabricar un Mapa Interactivo de nuestro barrio.&lt;/span&gt;&lt;/p&gt;\n&lt;p&gt;&lt;span style=\"font-family: georgia, palatino, serif;\"&gt;Pondremos vuestros dibujos de las tiendas y parques.&lt;/span&gt;&lt;br /&gt;&lt;span style=\"font-family: georgia, palatino, serif;\"&gt;Grabaremos vuestra voz contando secretos del barrio.&lt;/span&gt;&lt;br /&gt;&lt;span style=\"font-family: georgia, palatino, serif;\"&gt;¡Cualquier persona que pulse en el mapa podrá oírnos y vernos!&lt;/span&gt;&lt;br /&gt;&lt;span style=\"font-family: georgia, palatino, serif;\"&gt;Usaremos una herramienta genial llamada Genially. ¡Es muy fácil y divertida!&lt;/span&gt;&lt;/p&gt;\n&lt;p&gt;&lt;span style=\"font-family: georgia, palatino, serif;\"&gt;&lt;a href=\"https://view.genially.com/69b6cce63695ebf5939cb93b\" title=\"Mapa del barrio\" id=\"link_0\"&gt;https://view.genially.com/69b6cce63695ebf5939cb93b&lt;/a&gt;&lt;/span&gt;&lt;/p&gt;\n&lt;p&gt;&lt;span style=\"font-size: 8pt; font-family: georgia, palatino, serif;\"&gt;Autoría: Araceli Servián/ Recurso creado con Genially / Licencia: Creative Commons BY-NC-SA 4.0 &lt;/span&gt;&lt;/p&gt;\n&lt;p&gt;&lt;span style=\"font-size: 8pt; font-family: georgia, palatino, serif;\"&gt;Imágen: Fuente: Consejería de Desarrollo Educativo y Formación Profesional (Junta de Andalucía). Licencia: CC BY-NC-SA (Reconocimiento-NoComercial-CompartirIgual).&lt;/span&gt;&lt;br /&gt;&lt;span style=\"font-family: georgia, palatino, serif;\"&gt; &lt;/span&gt;&lt;/p&gt;","textFeedbackInput":"Mostrar retroalimentación","textFeedbackTextarea":""}</jsonProperties><odeComponentsOrder>1</odeComponentsOrder><odeComponentsProperties><odeComponentsProperty><key>visibility</key><value>true</value></odeComponentsProperty><odeComponentsProperty><key>teacherOnly</key><value>false</value></odeComponentsProperty><odeComponentsProperty><key>identifier</key><value/></odeComponentsProperty><odeComponentsProperty><key>cssClass</key><value/></odeComponentsProperty></odeComponentsProperties></odeComponent></odeComponents></odePagStructure></odePagStructures></odeNavStructure><odeNavStructure><odePageId>20260322190753LOOTAX</odePageId><odeParentPageId>20260322190753ENIYTU</odeParentPageId><pageName>Zona de investigación: nuestros mapas de recursos</pageName><odeNavStructureOrder>3</odeNavStructureOrder><odeNavStructureProperties><odeNavStructureProperty><key>titleNode</key><value>Zona de investigación: nuestros mapas de recursos</value></odeNavStructureProperty><odeNavStructureProperty><key>hidePageTitle</key><value>false</value></odeNavStructureProperty><odeNavStructureProperty><key>titleHtml</key><value/></odeNavStructureProperty><odeNavStructureProperty><key>editableInPage</key><value>false</value></odeNavStructureProperty><odeNavStructureProperty><key>titlePage</key><value>Zona de investigación: nuestros mapas de recursos</value></odeNavStructureProperty><odeNavStructureProperty><key>visibility</key><value>true</value></odeNavStructureProperty><odeNavStructureProperty><key>highlight</key><value>false</value></odeNavStructureProperty><odeNavStructureProperty><key>description</key><value/></odeNavStructureProperty></odeNavStructureProperties><odePagStructures><odePagStructure><odePageId>20260322190753LOOTAX</odePageId><odeBlockId>20260322190753DTMXGG</odeBlockId><blockName>Sitios que debemos visitar: Symbaloo</blockName><iconName>info</iconName><odePagStructureOrder>1</odePagStructureOrder><odePagStructureProperties><odePagStructureProperty><key>visibility</key><value>true</value></odePagStructureProperty><odePagStructureProperty><key>teacherOnly</key><value>false</value></odePagStructureProperty><odePagStructureProperty><key>allowToggle</key><value>true</value></odePagStructureProperty><odePagStructureProperty><key>minimized</key><value>false</value></odePagStructureProperty><odePagStructureProperty><key>identifier</key><value/></odePagStructureProperty><odePagStructureProperty><key>cssClass</key><value/></odePagStructureProperty></odePagStructureProperties><odeComponents><odeComponent><odePageId>20260322190753LOOTAX</odePageId><odeBlockId>20260322190753DTMXGG</odeBlockId><odeIdeviceId>202603221726058728EO</odeIdeviceId><odeIdeviceTypeName>text</odeIdeviceTypeName><htmlView>&lt;div class="exe-text-template"&gt;&lt;div class="textIdeviceContent"&gt;
            &lt;div class="exe-text-activity"&gt;
                &lt;div&gt;&lt;p style="text-align: right;"&gt;&lt;span style="font-family: georgia, palatino, serif;"&gt;&lt;span style="font-size: 14pt;"&gt;&lt;strong&gt;Sitios que debemos visitar 🚀&lt;/strong&gt;&lt;/span&gt;&lt;/span&gt;&lt;/p&gt;
&lt;p style="text-align: justify;"&gt;&lt;span style="font-family: georgia, palatino, serif;"&gt;Pulsad en los iconos para investigar y buscar información de nuestro barrio.&amp;nbsp;&lt;/span&gt;&lt;br&gt;&lt;/p&gt;
&lt;p&gt;&lt;a href="https://araceli1.symbaloo.com/home/mix/13ePH25OI7" id="link_1"&gt;https://araceli1.symbaloo.com/home/mix/13ePH25OI7&lt;/a&gt;&lt;/p&gt;
&lt;p&gt;&lt;span style="font-family: georgia, palatino, serif; font-size: 8pt;"&gt;Nota de Autoría: "Webmix de Symbaloo creado por Araceli Servián / Licencia CC BY-NC-SA".&lt;/span&gt;&lt;/p&gt;&lt;p class="clearfix"&gt;&lt;/p&gt;&lt;/div&gt;
            &lt;/div&gt;&lt;/div&gt;&lt;/div&gt;</htmlView><jsonProperties>{"ideviceId":"202603221726058728EO","textInfoDurationInput":"","textInfoDurationTextInput":"Duración","textInfoParticipantsInput":"","textInfoParticipantsTextInput":"Agrupamiento","textTextarea":"&lt;p style=\"text-align: right;\"&gt;&lt;span style=\"font-family: georgia, palatino, serif;\"&gt;&lt;span style=\"font-size: 14pt;\"&gt;&lt;strong&gt;Sitios que debemos visitar 🚀&lt;/strong&gt;&lt;/span&gt;&lt;/span&gt;&lt;/p&gt;\n&lt;p style=\"text-align: justify;\"&gt;&lt;span style=\"font-family: georgia, palatino, serif;\"&gt;Pulsad en los iconos para investigar y buscar información de nuestro barrio. &lt;/span&gt;&lt;br /&gt;&lt;/p&gt;\n&lt;p&gt;&lt;a href=\"https://araceli1.symbaloo.com/home/mix/13ePH25OI7\" id=\"link_1\"&gt;https://araceli1.symbaloo.com/home/mix/13ePH25OI7&lt;/a&gt;&lt;/p&gt;\n&lt;p&gt;&lt;span style=\"font-family: georgia, palatino, serif; font-size: 8pt;\"&gt;Nota de Autoría: \"Webmix de Symbaloo creado por Araceli Servián / Licencia CC BY-NC-SA\".&lt;/span&gt;&lt;/p&gt;","textFeedbackInput":"Mostrar retroalimentación","textFeedbackTextarea":""}</jsonProperties><odeComponentsOrder>1</odeComponentsOrder><odeComponentsProperties><odeComponentsProperty><key>visibility</key><value>true</value></odeComponentsProperty><odeComponentsProperty><key>teacherOnly</key><value>false</value></odeComponentsProperty><odeComponentsProperty><key>identifier</key><value/></odeComponentsProperty><odeComponentsProperty><key>cssClass</key><value/></odeComponentsProperty></odeComponentsProperties></odeComponent></odeComponents></odePagStructure><odePagStructure><odePageId>20260322190753LOOTAX</odePageId><odeBlockId>20260322190753YMIVZN</odeBlockId><blockName>Muro de ideas: Padlet</blockName><iconName/><odePagStructureOrder>2</odePagStructureOrder><odePagStructureProperties><odePagStructureProperty><key>visibility</key><value>true</value></odePagStructureProperty><odePagStructureProperty><key>teacherOnly</key><value>false</value></odePagStructureProperty><odePagStructureProperty><key>allowToggle</key><value>true</value></odePagStructureProperty><odePagStructureProperty><key>minimized</key><value>false</value></odePagStructureProperty><odePagStructureProperty><key>identifier</key><value/></odePagStructureProperty><odePagStructureProperty><key>cssClass</key><value/></odePagStructureProperty></odePagStructureProperties><odeComponents><odeComponent><odePageId>20260322190753LOOTAX</odePageId><odeBlockId>20260322190753YMIVZN</odeBlockId><odeIdeviceId>20260322173013515I4Z</odeIdeviceId><odeIdeviceTypeName>text</odeIdeviceTypeName><htmlView>&lt;div class="exe-text-template"&gt;&lt;div class="textIdeviceContent"&gt;
            &lt;div class="exe-text-activity"&gt;
                &lt;div&gt;&lt;p style="text-align: center;"&gt;&lt;span style="font-size: 14pt; font-family: georgia, palatino, serif;"&gt;&lt;strong&gt;📌 Nuestro Tablón de Notas: Fotos y Vídeos&lt;/strong&gt;&lt;/span&gt;&lt;/p&gt;
&lt;p style="text-align: justify;"&gt;&lt;span style="font-family: georgia, palatino, serif;"&gt;Aquí tenemos los vídeos de cómo usar la cámara y las fotos de ejemplo para nuestro mapa.&amp;nbsp;&lt;/span&gt;&lt;/p&gt;
&lt;p&gt;&lt;span style="font-family: georgia, palatino, serif;"&gt;&lt;a href="https://padlet.com/araceliservian97/mi-barrio-en-360-lsg5287xwrh9atnj"&gt;https://padlet.com/araceliservian97/mi-barrio-en-360-lsg5287xwrh9atnj&lt;/a&gt;&lt;/span&gt;&lt;/p&gt;
&lt;p&gt;&lt;span style="font-size: 8pt; font-family: georgia, palatino, serif;"&gt;Nota de Autoría: "Muro de Padlet creado por Araceli Servián / Licencia CC BY-NC-SA".&lt;/span&gt;&lt;/p&gt;&lt;p class="clearfix"&gt;&lt;/p&gt;&lt;/div&gt;
            &lt;/div&gt;&lt;/div&gt;&lt;/div&gt;</htmlView><jsonProperties>{"ideviceId":"20260322173013515I4Z","textInfoDurationInput":"","textInfoDurationTextInput":"Duración","textInfoParticipantsInput":"","textInfoParticipantsTextInput":"Agrupamiento","textTextarea":"&lt;p style=\"text-align: center;\"&gt;&lt;span style=\"font-size: 14pt; font-family: georgia, palatino, serif;\"&gt;&lt;strong&gt;📌 Nuestro Tablón de Notas: Fotos y Vídeos&lt;/strong&gt;&lt;/span&gt;&lt;/p&gt;\n&lt;p style=\"text-align: justify;\"&gt;&lt;span style=\"font-family: georgia, palatino, serif;\"&gt;Aquí tenemos los vídeos de cómo usar la cámara y las fotos de ejemplo para nuestro mapa. &lt;/span&gt;&lt;/p&gt;\n&lt;p&gt;&lt;span style=\"font-family: georgia, palatino, serif;\"&gt;&lt;a href=\"https://padlet.com/araceliservian97/mi-barrio-en-360-lsg5287xwrh9atnj\"&gt;https://padlet.com/araceliservian97/mi-barrio-en-360-lsg5287xwrh9atnj&lt;/a&gt;&lt;/span&gt;&lt;/p&gt;\n&lt;p&gt;&lt;span style=\"font-size: 8pt; font-family: georgia, palatino, serif;\"&gt;Nota de Autoría: \"Muro de Padlet creado por Araceli Servián / Licencia CC BY-NC-SA\".&lt;/span&gt;&lt;/p&gt;","textFeedbackInput":"Mostrar retroalimentación","textFeedbackTextarea":""}</jsonProperties><odeComponentsOrder>1</odeComponentsOrder><odeComponentsProperties><odeComponentsProperty><key>visibility</key><value>true</value></odeComponentsProperty><odeComponentsProperty><key>teacherOnly</key><value>false</value></odeComponentsProperty><odeComponentsProperty><key>identifier</key><value/></odeComponentsProperty><odeComponentsProperty><key>cssClass</key><value/></odeComponentsProperty></odeComponentsProperties></odeComponent></odeComponents></odePagStructure></odePagStructures></odeNavStructure><odeNavStructure><odePageId>20260322190753WLDGLO</odePageId><odeParentPageId>20260322190753ENIYTU</odeParentPageId><pageName>Nuestro camino: 8 sesiones de aventuras</pageName><odeNavStructureOrder>4</odeNavStructureOrder><odeNavStructureProperties><odeNavStructureProperty><key>titleNode</key><value/></odeNavStructureProperty><odeNavStructureProperty><key>hidePageTitle</key><value>false</value></odeNavStructureProperty><odeNavStructureProperty><key>titleHtml</key><value/></odeNavStructureProperty><odeNavStructureProperty><key>editableInPage</key><value>false</value></odeNavStructureProperty><odeNavStructureProperty><key>titlePage</key><value>Nuestro camino: 8 sesiones de aventuras</value></odeNavStructureProperty><odeNavStructureProperty><key>visibility</key><value>true</value></odeNavStructureProperty><odeNavStructureProperty><key>highlight</key><value>false</value></odeNavStructureProperty><odeNavStructureProperty><key>description</key><value/></odeNavStructureProperty></odeNavStructureProperties><odePagStructures><odePagStructure><odePageId>20260322190753WLDGLO</odePageId><odeBlockId>20260322190753GJZCJZ</odeBlockId><blockName>Nuestro mapa mental&amp;nbsp;</blockName><iconName>diary_alt</iconName><odePagStructureOrder>1</odePagStructureOrder><odePagStructureProperties><odePagStructureProperty><key>visibility</key><value>true</value></odePagStructureProperty><odePagStructureProperty><key>teacherOnly</key><value>false</value></odePagStructureProperty><odePagStructureProperty><key>allowToggle</key><value>true</value></odePagStructureProperty><odePagStructureProperty><key>minimized</key><value>false</value></odePagStructureProperty><odePagStructureProperty><key>identifier</key><value/></odePagStructureProperty><odePagStructureProperty><key>cssClass</key><value/></odePagStructureProperty></odePagStructureProperties><odeComponents><odeComponent><odePageId>20260322190753WLDGLO</odePageId><odeBlockId>20260322190753GJZCJZ</odeBlockId><odeIdeviceId>20260322174408506N9C</odeIdeviceId><odeIdeviceTypeName>text</odeIdeviceTypeName><htmlView>&lt;div class="exe-text-template"&gt;&lt;div class="textIdeviceContent"&gt;
            &lt;div class="exe-text-activity"&gt;
                &lt;div&gt;&lt;p&gt;&lt;span style="font-family: georgia, palatino, serif;"&gt;¡Mirad todo lo que vamos a aprender en estas 3 semanas!&lt;/span&gt;&lt;/p&gt;
&lt;p&gt;&lt;img src="{{context_path}}/20260322174408506N9C/tarea7.1._Servian_Araceli.png" title="Mapa mental del proyecto " width="807" height="394" alt="Mapa mental del proyecto "&gt;&lt;/p&gt;
&lt;p&gt;&lt;span style="font-size: 8pt; font-family: georgia, palatino, serif;"&gt;Mapa mental elaborado por Araceli Servián con Mindmeister.&amp;nbsp;&lt;/span&gt;&amp;nbsp;&lt;/p&gt;
&lt;table border="1" class="exe-table" style="width: 100%; height: 144px;"&gt;
&lt;tbody&gt;
&lt;tr style="height: 26.5px;"&gt;
&lt;td style="width: 8.49401%; height: 26.5px; text-align: center;"&gt;&lt;span style="background-color: #fbeeb8;"&gt;Sesión&lt;/span&gt;&lt;/td&gt;
&lt;td style="width: 91.506%; height: 26.5px; text-align: center;"&gt;&lt;span style="background-color: #fbeeb8;"&gt;¿Qué vamos a hacer?&lt;/span&gt;&lt;/td&gt;
&lt;/tr&gt;
&lt;tr style="height: 34px;"&gt;
&lt;td style="width: 8.49401%; height: 34px; text-align: center;"&gt;&lt;span style="background-color: #f8cac6;"&gt;1 y 2&lt;/span&gt;&lt;/td&gt;
&lt;td style="width: 91.506%; height: 34px;"&gt;&lt;span style="background-color: #f8cac6;"&gt;Preparación: Elegimos los puntos clave y aprendemos a usar la tablet.&lt;/span&gt;&lt;/td&gt;
&lt;/tr&gt;
&lt;tr style="height: 31px;"&gt;
&lt;td style="width: 8.49401%; height: 31px; text-align: center;"&gt;&lt;span style="background-color: #eccafa;"&gt;3 y 4&lt;/span&gt;&lt;/td&gt;
&lt;td style="width: 91.506%; height: 31px;"&gt;&lt;span style="background-color: #eccafa;"&gt;&amp;nbsp;&lt;strong&gt;&lt;/strong&gt;Acción: ¡Salida al barrio! Safari fotográfico y entrevistas breves.&lt;/span&gt;&lt;/td&gt;
&lt;/tr&gt;
&lt;tr style="height: 26px;"&gt;
&lt;td style="width: 8.49401%; height: 26px; text-align: center;"&gt;&lt;span style="background-color: #c2e0f4;"&gt;5 y 7&lt;/span&gt;&lt;/td&gt;
&lt;td style="width: 91.506%; height: 26px;"&gt;&lt;span style="background-color: #c2e0f4;"&gt;Creación: Dibujo artístico de los lugares y grabación de audios.&lt;/span&gt;&lt;/td&gt;
&lt;/tr&gt;
&lt;tr style="height: 26.5px;"&gt;
&lt;td style="width: 8.49401%; height: 26.5px; text-align: center;"&gt;&lt;span style="background-color: #bfedd2;"&gt;8&amp;nbsp;&lt;/span&gt;&lt;/td&gt;
&lt;td style="width: 91.506%; height: 26.5px;"&gt;&lt;span style="background-color: #bfedd2;"&gt;Estreno: Presentación del Mapa Interactivo.&lt;/span&gt;&lt;/td&gt;
&lt;/tr&gt;
&lt;/tbody&gt;
&lt;/table&gt;
&lt;p&gt;&lt;br&gt;&lt;/p&gt;
&lt;p&gt;&lt;br&gt;&lt;/p&gt;
&lt;p&gt;&lt;br&gt;&lt;/p&gt;&lt;p class="clearfix"&gt;&lt;/p&gt;&lt;/div&gt;
            &lt;/div&gt;&lt;/div&gt;&lt;/div&gt;</htmlView><jsonProperties>{"ideviceId":"20260322174408506N9C","textInfoDurationInput":"","textInfoDurationTextInput":"Duración","textInfoParticipantsInput":"","textInfoParticipantsTextInput":"Agrupamiento","textTextarea":"&lt;p&gt;&lt;span style=\"font-family: georgia, palatino, serif;\"&gt;¡Mirad todo lo que vamos a aprender en estas 3 semanas!&lt;/span&gt;&lt;/p&gt;\n&lt;p&gt;&lt;img src=\"{{context_path}}/20260322174408506N9C/tarea7.1._Servian_Araceli.png\" title=\"Mapa mental del proyecto \" width=\"807\" height=\"394\" alt=\"Mapa mental del proyecto \" /&gt;&lt;/p&gt;\n&lt;p&gt;&lt;span style=\"font-size: 8pt; font-family: georgia, palatino, serif;\"&gt;Mapa mental elaborado por Araceli Servián con Mindmeister. &lt;/span&gt; &lt;/p&gt;\n&lt;table border=\"1\" class=\"exe-table\" style=\"width: 100%; height: 144px;\"&gt;\n&lt;tbody&gt;\n&lt;tr style=\"height: 26.5px;\"&gt;\n&lt;td style=\"width: 8.49401%; height: 26.5px; text-align: center;\"&gt;&lt;span style=\"background-color: #fbeeb8;\"&gt;Sesión&lt;/span&gt;&lt;/td&gt;\n&lt;td style=\"width: 91.506%; height: 26.5px; text-align: center;\"&gt;&lt;span style=\"background-color: #fbeeb8;\"&gt;¿Qué vamos a hacer?&lt;/span&gt;&lt;/td&gt;\n&lt;/tr&gt;\n&lt;tr style=\"height: 34px;\"&gt;\n&lt;td style=\"width: 8.49401%; height: 34px; text-align: center;\"&gt;&lt;span style=\"background-color: #f8cac6;\"&gt;1 y 2&lt;/span&gt;&lt;/td&gt;\n&lt;td style=\"width: 91.506%; height: 34px;\"&gt;&lt;span style=\"background-color: #f8cac6;\"&gt;Preparación: Elegimos los puntos clave y aprendemos a usar la tablet.&lt;/span&gt;&lt;/td&gt;\n&lt;/tr&gt;\n&lt;tr style=\"height: 31px;\"&gt;\n&lt;td style=\"width: 8.49401%; height: 31px; text-align: center;\"&gt;&lt;span style=\"background-color: #eccafa;\"&gt;3 y 4&lt;/span&gt;&lt;/td&gt;\n&lt;td style=\"width: 91.506%; height: 31px;\"&gt;&lt;span style=\"background-color: #eccafa;\"&gt; &lt;strong&gt;&lt;/strong&gt;Acción: ¡Salida al barrio! Safari fotográfico y entrevistas breves.&lt;/span&gt;&lt;/td&gt;\n&lt;/tr&gt;\n&lt;tr style=\"height: 26px;\"&gt;\n&lt;td style=\"width: 8.49401%; height: 26px; text-align: center;\"&gt;&lt;span style=\"background-color: #c2e0f4;\"&gt;5 y 7&lt;/span&gt;&lt;/td&gt;\n&lt;td style=\"width: 91.506%; height: 26px;\"&gt;&lt;span style=\"background-color: #c2e0f4;\"&gt;Creación: Dibujo artístico de los lugares y grabación de audios.&lt;/span&gt;&lt;/td&gt;\n&lt;/tr&gt;\n&lt;tr style=\"height: 26.5px;\"&gt;\n&lt;td style=\"width: 8.49401%; height: 26.5px; text-align: center;\"&gt;&lt;span style=\"background-color: #bfedd2;\"&gt;8 &lt;/span&gt;&lt;/td&gt;\n&lt;td style=\"width: 91.506%; height: 26.5px;\"&gt;&lt;span style=\"background-color: #bfedd2;\"&gt;Estreno: Presentación del Mapa Interactivo.&lt;/span&gt;&lt;/td&gt;\n&lt;/tr&gt;\n&lt;/tbody&gt;\n&lt;/table&gt;\n&lt;p&gt;&lt;br /&gt;&lt;/p&gt;\n&lt;p&gt;&lt;br /&gt;&lt;/p&gt;\n&lt;p&gt;&lt;br /&gt;&lt;/p&gt;","textFeedbackInput":"Mostrar retroalimentación","textFeedbackTextarea":""}</jsonProperties><odeComponentsOrder>1</odeComponentsOrder><odeComponentsProperties><odeComponentsProperty><key>visibility</key><value>true</value></odeComponentsProperty><odeComponentsProperty><key>teacherOnly</key><value>false</value></odeComponentsProperty><odeComponentsProperty><key>identifier</key><value/></odeComponentsProperty><odeComponentsProperty><key>cssClass</key><value/></odeComponentsProperty></odeComponentsProperties></odeComponent></odeComponents></odePagStructure></odePagStructures></odeNavStructure><odeNavStructure><odePageId>20260322190753BBONLV</odePageId><odeParentPageId>20260322190753ENIYTU</odeParentPageId><pageName>¿Cómo evaluamos nuestro proyecto?</pageName><odeNavStructureOrder>5</odeNavStructureOrder><odeNavStructureProperties><odeNavStructureProperty><key>titleNode</key><value>¿Cómo evaluamos nuestro proyecto?</value></odeNavStructureProperty><odeNavStructureProperty><key>hidePageTitle</key><value>false</value></odeNavStructureProperty><odeNavStructureProperty><key>titleHtml</key><value/></odeNavStructureProperty><odeNavStructureProperty><key>editableInPage</key><value>false</value></odeNavStructureProperty><odeNavStructureProperty><key>titlePage</key><value>¿Cómo evaluamos nuestro proyecto?</value></odeNavStructureProperty><odeNavStructureProperty><key>visibility</key><value>true</value></odeNavStructureProperty><odeNavStructureProperty><key>highlight</key><value>false</value></odeNavStructureProperty><odeNavStructureProperty><key>description</key><value/></odeNavStructureProperty></odeNavStructureProperties><odePagStructures><odePagStructure><odePageId>20260322190753BBONLV</odePageId><odeBlockId>20260322190753XIZKNT</odeBlockId><blockName>Evaluación</blockName><iconName>objectives</iconName><odePagStructureOrder>1</odePagStructureOrder><odePagStructureProperties><odePagStructureProperty><key>visibility</key><value>true</value></odePagStructureProperty><odePagStructureProperty><key>teacherOnly</key><value>false</value></odePagStructureProperty><odePagStructureProperty><key>allowToggle</key><value>true</value></odePagStructureProperty><odePagStructureProperty><key>minimized</key><value>false</value></odePagStructureProperty><odePagStructureProperty><key>identifier</key><value/></odePagStructureProperty><odePagStructureProperty><key>cssClass</key><value/></odePagStructureProperty></odePagStructureProperties><odeComponents><odeComponent><odePageId>20260322190753BBONLV</odePageId><odeBlockId>20260322190753XIZKNT</odeBlockId><odeIdeviceId>20260322192839074OV0</odeIdeviceId><odeIdeviceTypeName>text</odeIdeviceTypeName><htmlView>&lt;div class="exe-text-template"&gt;&lt;div class="textIdeviceContent"&gt;
            &lt;div class="exe-text-activity"&gt;
                &lt;div&gt;&lt;p style="text-align: center;"&gt;&lt;span style="font-size: 14pt; font-family: georgia, palatino, serif;"&gt;&lt;strong&gt;🌟 ¿Qué vamos a mirar en vuestro trabajo?&lt;/strong&gt;&lt;/span&gt;&lt;/p&gt;
&lt;p style="text-align: justify;"&gt;&lt;span style="font-family: georgia, palatino, serif;"&gt;¿Cómo vamos a evaluar? Para este proyecto utilizaremos dos herramientas principales:&lt;/span&gt;&lt;/p&gt;
&lt;ul&gt;
&lt;li style="text-align: justify;"&gt;&lt;span style="font-family: georgia, palatino, serif;"&gt;Rúbrica del Mapa Interactivo: Para evaluar el resultado final en Genially. &lt;/span&gt;&lt;/li&gt;
&lt;li style="text-align: justify;"&gt;&lt;span style="font-family: georgia, palatino, serif;"&gt;Checklist de Observación: Para evaluar el comportamiento y el trabajo durante la salida al barrio.&lt;/span&gt;&lt;br&gt;&lt;span style="font-family: georgia, palatino, serif;"&gt;&amp;nbsp;&lt;/span&gt;&lt;/li&gt;
&lt;/ul&gt;&lt;p class="clearfix"&gt;&lt;/p&gt;&lt;/div&gt;
            &lt;/div&gt;&lt;/div&gt;&lt;/div&gt;</htmlView><jsonProperties>{"ideviceId":"20260322192839074OV0","textInfoDurationInput":"","textInfoDurationTextInput":"Duración","textInfoParticipantsInput":"","textInfoParticipantsTextInput":"Agrupamiento","textTextarea":"&lt;p style=\"text-align: center;\"&gt;&lt;span style=\"font-size: 14pt; font-family: georgia, palatino, serif;\"&gt;&lt;strong&gt;🌟 ¿Qué vamos a mirar en vuestro trabajo?&lt;/strong&gt;&lt;/span&gt;&lt;/p&gt;\n&lt;p style=\"text-align: justify;\"&gt;&lt;span style=\"font-family: georgia, palatino, serif;\"&gt;¿Cómo vamos a evaluar? Para este proyecto utilizaremos dos herramientas principales:&lt;/span&gt;&lt;/p&gt;\n&lt;ul&gt;\n&lt;li style=\"text-align: justify;\"&gt;&lt;span style=\"font-family: georgia, palatino, serif;\"&gt;Rúbrica del Mapa Interactivo: Para evaluar el resultado final en Genially. &lt;/span&gt;&lt;/li&gt;\n&lt;li style=\"text-align: justify;\"&gt;&lt;span style=\"font-family: georgia, palatino, serif;\"&gt;Checklist de Observación: Para evaluar el comportamiento y el trabajo durante la salida al barrio.&lt;/span&gt;&lt;br /&gt;&lt;span style=\"font-family: georgia, palatino, serif;\"&gt; &lt;/span&gt;&lt;/li&gt;\n&lt;/ul&gt;","textFeedbackInput":"Mostrar retroalimentación","textFeedbackTextarea":""}</jsonProperties><odeComponentsOrder>1</odeComponentsOrder><odeComponentsProperties><odeComponentsProperty><key>visibility</key><value>true</value></odeComponentsProperty><odeComponentsProperty><key>teacherOnly</key><value>false</value></odeComponentsProperty><odeComponentsProperty><key>identifier</key><value/></odeComponentsProperty><odeComponentsProperty><key>cssClass</key><value/></odeComponentsProperty></odeComponentsProperties></odeComponent></odeComponents></odePagStructure><odePagStructure><odePageId>20260322190753BBONLV</odePageId><odeBlockId>20260322190753XHUODM</odeBlockId><blockName>Nuestras rúbricas de evaluación&amp;nbsp;</blockName><iconName>objectives</iconName><odePagStructureOrder>2</odePagStructureOrder><odePagStructureProperties><odePagStructureProperty><key>visibility</key><value>true</value></odePagStructureProperty><odePagStructureProperty><key>teacherOnly</key><value>false</value></odePagStructureProperty><odePagStructureProperty><key>allowToggle</key><value>true</value></odePagStructureProperty><odePagStructureProperty><key>minimized</key><value>false</value></odePagStructureProperty><odePagStructureProperty><key>identifier</key><value/></odePagStructureProperty><odePagStructureProperty><key>cssClass</key><value/></odePagStructureProperty></odePagStructureProperties><odeComponents><odeComponent><odePageId>20260322190753BBONLV</odePageId><odeBlockId>20260322190753XHUODM</odeBlockId><odeIdeviceId>20260322193247608F8X</odeIdeviceId><odeIdeviceTypeName>text</odeIdeviceTypeName><htmlView>&lt;div class="exe-text-template"&gt;&lt;div class="textIdeviceContent"&gt;
            &lt;div class="exe-text-activity"&gt;
                &lt;div&gt;&lt;p&gt;&lt;span style="font-family: georgia, palatino, serif;"&gt;Tendremos en cuenta estos niveles:&lt;/span&gt;&lt;/p&gt;
&lt;ul&gt;
&lt;li&gt;&lt;span style="font-family: georgia, palatino, serif;"&gt;Insuficiente (1): 🔴 (Necesito ayuda)&lt;/span&gt;&lt;/li&gt;
&lt;li&gt;&lt;span style="font-family: georgia, palatino, serif;"&gt;Suficiente (2): 🟠 (Voy por buen camino)&lt;/span&gt;&lt;/li&gt;
&lt;li&gt;&lt;span style="font-family: georgia, palatino, serif;"&gt;Bien (3): 🟢 (¡Lo he conseguido!)&lt;/span&gt;&lt;/li&gt;
&lt;li&gt;&lt;span style="font-family: georgia, palatino, serif;"&gt;Excelente (4): 🌟 (¡Soy un súper reportero!)&lt;/span&gt;&lt;br&gt;&lt;span style="font-family: georgia, palatino, serif;"&gt;&amp;nbsp;&lt;/span&gt;&lt;/li&gt;
&lt;/ul&gt;
&lt;table border="1" class="exe-table" style="width: 100%;"&gt;
&lt;tbody&gt;
&lt;tr&gt;
&lt;td style="width: 22.6562%; text-align: center;"&gt;&lt;span style="font-family: georgia, palatino, serif;"&gt;&lt;strong&gt;Criterios de Evaluación&lt;/strong&gt;&lt;/span&gt;&lt;/td&gt;
&lt;td style="width: 18.125%; text-align: center;"&gt;&lt;span style="font-family: georgia, palatino, serif;"&gt;&lt;strong&gt;Insuficiente (1)&lt;/strong&gt;&lt;/span&gt;&lt;/td&gt;
&lt;td style="width: 18.125%; text-align: center;"&gt;&lt;span style="font-family: georgia, palatino, serif;"&gt;&lt;strong&gt;Suficiente (2)&lt;/strong&gt;&lt;/span&gt;&lt;/td&gt;
&lt;td style="width: 18.125%; text-align: center;"&gt;&lt;span style="font-family: georgia, palatino, serif;"&gt;&lt;strong&gt;Bien (3)&lt;/strong&gt;&lt;/span&gt;&lt;/td&gt;
&lt;td style="width: 22.661%; text-align: center;"&gt;&lt;span style="font-family: georgia, palatino, serif;"&gt;&lt;strong&gt;Excelente (4)&lt;/strong&gt;&lt;/span&gt;&lt;/td&gt;
&lt;/tr&gt;
&lt;tr&gt;
&lt;td style="width: 22.6562%; text-align: justify;"&gt;&lt;span style="font-family: georgia, palatino, serif;"&gt;Creatividad y Expresión Artística&lt;/span&gt;&lt;/td&gt;
&lt;td style="width: 18.125%; text-align: justify;"&gt;&lt;span style="font-family: georgia, palatino, serif;"&gt;No incluye fotografías ni dibujos, o estos no guardan relación con el barrio.&lt;/span&gt;&lt;/td&gt;
&lt;td style="width: 18.125%; text-align: justify;"&gt;&lt;span style="font-family: georgia, palatino, serif;"&gt;Incluye algunas fotos o dibujos, pero son escasos o poco claros.&lt;/span&gt;&lt;/td&gt;
&lt;td style="width: 18.125%; text-align: justify;"&gt;&lt;span style="font-family: georgia, palatino, serif;"&gt;Incluye fotos y dibujos claros que representan bien los lugares del barrio.&lt;/span&gt;&lt;/td&gt;
&lt;td style="width: 22.661%; text-align: justify;"&gt;&lt;span style="font-family: georgia, palatino, serif;"&gt;Combina fotos y dibujos con mucho detalle, originalidad y excelente presentación.&lt;/span&gt;&lt;/td&gt;
&lt;/tr&gt;
&lt;tr&gt;
&lt;td style="width: 22.6562%; text-align: justify;"&gt;&lt;span style="font-family: georgia, palatino, serif;"&gt;Comunicación Oral (Audios)&lt;/span&gt;&lt;/td&gt;
&lt;td style="width: 18.125%; text-align: justify;"&gt;&lt;span style="font-family: georgia, palatino, serif;"&gt;No hay audios o no se entiende nada de lo que dice.&lt;/span&gt;&lt;/td&gt;
&lt;td style="width: 18.125%; text-align: justify;"&gt;&lt;span style="font-family: georgia, palatino, serif;"&gt;Los audios son muy cortos, se oyen con mucho ruido o cuesta entender el mensaje.&lt;/span&gt;&lt;/td&gt;
&lt;td style="width: 18.125%; text-align: justify;"&gt;&lt;span style="font-family: georgia, palatino, serif;"&gt;Los audios son claros y explican los puntos del mapa de forma sencilla.&lt;/span&gt;&lt;/td&gt;
&lt;td style="width: 22.661%; text-align: justify;"&gt;&lt;span style="font-family: georgia, palatino, serif;"&gt;Los audios son muy claros, usa un tono adecuado y explica los lugares con entusiasmo.&lt;/span&gt;&lt;/td&gt;
&lt;/tr&gt;
&lt;tr&gt;
&lt;td style="width: 22.6562%; text-align: justify;"&gt;&lt;span style="font-family: georgia, palatino, serif;"&gt;Competencia Digital Responsable&lt;/span&gt;&lt;/td&gt;
&lt;td style="width: 18.125%; text-align: justify;"&gt;&lt;span style="font-family: georgia, palatino, serif;"&gt;Aparecen personas identificables sin permiso o fotos inapropiadas.&lt;/span&gt;&lt;/td&gt;
&lt;td style="width: 18.125%; text-align: justify;"&gt;&lt;span style="font-family: georgia, palatino, serif;"&gt;Aparece alguna persona de fondo, pero intenta respetar la privacidad.&lt;/span&gt;&lt;/td&gt;
&lt;td style="width: 18.125%; text-align: justify;"&gt;
&lt;p&gt;&lt;span style="font-family: georgia, palatino, serif;"&gt;Respeta la privacidad; en las fotos solo se ven lugares u objetos del barrio.&lt;/span&gt;&lt;/p&gt;
&lt;p&gt;&lt;/p&gt;
&lt;/td&gt;
&lt;td style="width: 22.661%; text-align: justify;"&gt;&lt;span style="font-family: georgia, palatino, serif;"&gt;Es ejemplar: no sale nadie y explica por qué es importante proteger la imagen de los demás.&lt;/span&gt;&lt;/td&gt;
&lt;/tr&gt;
&lt;tr&gt;
&lt;td style="width: 22.6562%; text-align: justify;"&gt;&lt;span style="font-family: georgia, palatino, serif;"&gt;Habilidad Tecnológica (Navegación)&lt;/span&gt;&lt;/td&gt;
&lt;td style="width: 18.125%; text-align: justify;"&gt;&lt;span style="font-family: georgia, palatino, serif;"&gt;El mapa no funciona o es imposible navegar por él.&lt;/span&gt;&lt;/td&gt;
&lt;td style="width: 18.125%; text-align: justify;"&gt;&lt;span style="font-family: georgia, palatino, serif;"&gt;El mapa funciona, pero es difícil encontrar los botones o puntos interactivos.&lt;/span&gt;&lt;/td&gt;
&lt;td style="width: 18.125%; text-align: justify;"&gt;&lt;span style="font-family: georgia, palatino, serif;"&gt;El mapa está organizado y se puede navegar por los puntos principales sin ayuda.&lt;/span&gt;&lt;/td&gt;
&lt;td style="width: 22.661%; text-align: justify;"&gt;&lt;span style="font-family: georgia, palatino, serif;"&gt;El mapa es muy intuitivo, todos los elementos funcionan perfecto y es fácil de usar.&lt;/span&gt;&lt;/td&gt;
&lt;/tr&gt;
&lt;/tbody&gt;
&lt;/table&gt;&lt;p class="clearfix"&gt;&lt;/p&gt;&lt;/div&gt;
            &lt;/div&gt;&lt;/div&gt;&lt;/div&gt;</htmlView><jsonProperties>{"ideviceId":"20260322193247608F8X","textInfoDurationInput":"","textInfoDurationTextInput":"Duración","textInfoParticipantsInput":"","textInfoParticipantsTextInput":"Agrupamiento","textTextarea":"&lt;p&gt;&lt;span style=\"font-family: georgia, palatino, serif;\"&gt;Tendremos en cuenta estos niveles:&lt;/span&gt;&lt;/p&gt;\n&lt;ul&gt;\n&lt;li&gt;&lt;span style=\"font-family: georgia, palatino, serif;\"&gt;Insuficiente (1): 🔴 (Necesito ayuda)&lt;/span&gt;&lt;/li&gt;\n&lt;li&gt;&lt;span style=\"font-family: georgia, palatino, serif;\"&gt;Suficiente (2): 🟠 (Voy por buen camino)&lt;/span&gt;&lt;/li&gt;\n&lt;li&gt;&lt;span style=\"font-family: georgia, palatino, serif;\"&gt;Bien (3): 🟢 (¡Lo he conseguido!)&lt;/span&gt;&lt;/li&gt;\n&lt;li&gt;&lt;span style=\"font-family: georgia, palatino, serif;\"&gt;Excelente (4): 🌟 (¡Soy un súper reportero!)&lt;/span&gt;&lt;br /&gt;&lt;span style=\"font-family: georgia, palatino, serif;\"&gt; &lt;/span&gt;&lt;/li&gt;\n&lt;/ul&gt;\n&lt;table border=\"1\" class=\"exe-table\" style=\"width: 100%;\"&gt;\n&lt;tbody&gt;\n&lt;tr&gt;\n&lt;td style=\"width: 22.6562%; text-align: center;\"&gt;&lt;span style=\"font-family: georgia, palatino, serif;\"&gt;&lt;strong&gt;Criterios de Evaluación&lt;/strong&gt;&lt;/span&gt;&lt;/td&gt;\n&lt;td style=\"width: 18.125%; text-align: center;\"&gt;&lt;span style=\"font-family: georgia, palatino, serif;\"&gt;&lt;strong&gt;Insuficiente (1)&lt;/strong&gt;&lt;/span&gt;&lt;/td&gt;\n&lt;td style=\"width: 18.125%; text-align: center;\"&gt;&lt;span style=\"font-family: georgia, palatino, serif;\"&gt;&lt;strong&gt;Suficiente (2)&lt;/strong&gt;&lt;/span&gt;&lt;/td&gt;\n&lt;td style=\"width: 18.125%; text-align: center;\"&gt;&lt;span style=\"font-family: georgia, palatino, serif;\"&gt;&lt;strong&gt;Bien (3)&lt;/strong&gt;&lt;/span&gt;&lt;/td&gt;\n&lt;td style=\"width: 22.661%; text-align: center;\"&gt;&lt;span style=\"font-family: georgia, palatino, serif;\"&gt;&lt;strong&gt;Excelente (4)&lt;/strong&gt;&lt;/span&gt;&lt;/td&gt;\n&lt;/tr&gt;\n&lt;tr&gt;\n&lt;td style=\"width: 22.6562%; text-align: justify;\"&gt;&lt;span style=\"font-family: georgia, palatino, serif;\"&gt;Creatividad y Expresión Artística&lt;/span&gt;&lt;/td&gt;\n&lt;td style=\"width: 18.125%; text-align: justify;\"&gt;&lt;span style=\"font-family: georgia, palatino, serif;\"&gt;No incluye fotografías ni dibujos, o estos no guardan relación con el barrio.&lt;/span&gt;&lt;/td&gt;\n&lt;td style=\"width: 18.125%; text-align: justify;\"&gt;&lt;span style=\"font-family: georgia, palatino, serif;\"&gt;Incluye algunas fotos o dibujos, pero son escasos o poco claros.&lt;/span&gt;&lt;/td&gt;\n&lt;td style=\"width: 18.125%; text-align: justify;\"&gt;&lt;span style=\"font-family: georgia, palatino, serif;\"&gt;Incluye fotos y dibujos claros que representan bien los lugares del barrio.&lt;/span&gt;&lt;/td&gt;\n&lt;td style=\"width: 22.661%; text-align: justify;\"&gt;&lt;span style=\"font-family: georgia, palatino, serif;\"&gt;Combina fotos y dibujos con mucho detalle, originalidad y excelente presentación.&lt;/span&gt;&lt;/td&gt;\n&lt;/tr&gt;\n&lt;tr&gt;\n&lt;td style=\"width: 22.6562%; text-align: justify;\"&gt;&lt;span style=\"font-family: georgia, palatino, serif;\"&gt;Comunicación Oral (Audios)&lt;/span&gt;&lt;/td&gt;\n&lt;td style=\"width: 18.125%; text-align: justify;\"&gt;&lt;span style=\"font-family: georgia, palatino, serif;\"&gt;No hay audios o no se entiende nada de lo que dice.&lt;/span&gt;&lt;/td&gt;\n&lt;td style=\"width: 18.125%; text-align: justify;\"&gt;&lt;span style=\"font-family: georgia, palatino, serif;\"&gt;Los audios son muy cortos, se oyen con mucho ruido o cuesta entender el mensaje.&lt;/span&gt;&lt;/td&gt;\n&lt;td style=\"width: 18.125%; text-align: justify;\"&gt;&lt;span style=\"font-family: georgia, palatino, serif;\"&gt;Los audios son claros y explican los puntos del mapa de forma sencilla.&lt;/span&gt;&lt;/td&gt;\n&lt;td style=\"width: 22.661%; text-align: justify;\"&gt;&lt;span style=\"font-family: georgia, palatino, serif;\"&gt;Los audios son muy claros, usa un tono adecuado y explica los lugares con entusiasmo.&lt;/span&gt;&lt;/td&gt;\n&lt;/tr&gt;\n&lt;tr&gt;\n&lt;td style=\"width: 22.6562%; text-align: justify;\"&gt;&lt;span style=\"font-family: georgia, palatino, serif;\"&gt;Competencia Digital Responsable&lt;/span&gt;&lt;/td&gt;\n&lt;td style=\"width: 18.125%; text-align: justify;\"&gt;&lt;span style=\"font-family: georgia, palatino, serif;\"&gt;Aparecen personas identificables sin permiso o fotos inapropiadas.&lt;/span&gt;&lt;/td&gt;\n&lt;td style=\"width: 18.125%; text-align: justify;\"&gt;&lt;span style=\"font-family: georgia, palatino, serif;\"&gt;Aparece alguna persona de fondo, pero intenta respetar la privacidad.&lt;/span&gt;&lt;/td&gt;\n&lt;td style=\"width: 18.125%; text-align: justify;\"&gt;\n&lt;p&gt;&lt;span style=\"font-family: georgia, palatino, serif;\"&gt;Respeta la privacidad; en las fotos solo se ven lugares u objetos del barrio.&lt;/span&gt;&lt;/p&gt;\n&lt;p&gt;&lt;/p&gt;\n&lt;/td&gt;\n&lt;td style=\"width: 22.661%; text-align: justify;\"&gt;&lt;span style=\"font-family: georgia, palatino, serif;\"&gt;Es ejemplar: no sale nadie y explica por qué es importante proteger la imagen de los demás.&lt;/span&gt;&lt;/td&gt;\n&lt;/tr&gt;\n&lt;tr&gt;\n&lt;td style=\"width: 22.6562%; text-align: justify;\"&gt;&lt;span style=\"font-family: georgia, palatino, serif;\"&gt;Habilidad Tecnológica (Navegación)&lt;/span&gt;&lt;/td&gt;\n&lt;td style=\"width: 18.125%; text-align: justify;\"&gt;&lt;span style=\"font-family: georgia, palatino, serif;\"&gt;El mapa no funciona o es imposible navegar por él.&lt;/span&gt;&lt;/td&gt;\n&lt;td style=\"width: 18.125%; text-align: justify;\"&gt;&lt;span style=\"font-family: georgia, palatino, serif;\"&gt;El mapa funciona, pero es difícil encontrar los botones o puntos interactivos.&lt;/span&gt;&lt;/td&gt;\n&lt;td style=\"width: 18.125%; text-align: justify;\"&gt;&lt;span style=\"font-family: georgia, palatino, serif;\"&gt;El mapa está organizado y se puede navegar por los puntos principales sin ayuda.&lt;/span&gt;&lt;/td&gt;\n&lt;td style=\"width: 22.661%; text-align: justify;\"&gt;&lt;span style=\"font-family: georgia, palatino, serif;\"&gt;El mapa es muy intuitivo, todos los elementos funcionan perfecto y es fácil de usar.&lt;/span&gt;&lt;/td&gt;\n&lt;/tr&gt;\n&lt;/tbody&gt;\n&lt;/table&gt;","textFeedbackInput":"Mostrar retroalimentación","textFeedbackTextarea":""}</jsonProperties><odeComponentsOrder>1</odeComponentsOrder><odeComponentsProperties><odeComponentsProperty><key>visibility</key><value>true</value></odeComponentsProperty><odeComponentsProperty><key>teacherOnly</key><value>false</value></odeComponentsProperty><odeComponentsProperty><key>identifier</key><value/></odeComponentsProperty><odeComponentsProperty><key>cssClass</key><value/></odeComponentsProperty></odeComponentsProperties></odeComponent></odeComponents></odePagStructure><odePagStructure><odePageId>20260322190753BBONLV</odePageId><odeBlockId>20260322190753SOWTKN</odeBlockId><blockName>"Hoja de Misión: Salida al Barrio" (Checklist)</blockName><iconName>stop</iconName><odePagStructureOrder>3</odePagStructureOrder><odePagStructureProperties><odePagStructureProperty><key>visibility</key><value>true</value></odePagStructureProperty><odePagStructureProperty><key>teacherOnly</key><value>false</value></odePagStructureProperty><odePagStructureProperty><key>allowToggle</key><value>true</value></odePagStructureProperty><odePagStructureProperty><key>minimized</key><value>false</value></odePagStructureProperty><odePagStructureProperty><key>identifier</key><value/></odePagStructureProperty><odePagStructureProperty><key>cssClass</key><value/></odePagStructureProperty></odePagStructureProperties><odeComponents><odeComponent><odePageId>20260322190753BBONLV</odePageId><odeBlockId>20260322190753SOWTKN</odeBlockId><odeIdeviceId>20260322193958270MZV</odeIdeviceId><odeIdeviceTypeName>text</odeIdeviceTypeName><htmlView>&lt;div class="exe-text-template"&gt;&lt;div class="textIdeviceContent"&gt;
            &lt;div class="exe-text-activity"&gt;
                &lt;div&gt;&lt;p&gt;"Hoja de Misión: Salida al Barrio" (Checklist)&lt;/p&gt;
&lt;p&gt;Chicos y chicas, mientras paseamos por el barrio, vuestra maestra llevará esta lista para ver qué bien trabajáis en equipo y cómo cuidáis vuestra tablet. ¡Seguro que todos conseguís muchos SÍ!"&lt;br&gt;&amp;nbsp;&lt;/p&gt;
&lt;table border="1" class="exe-table" style="width: 100%; height: 122px;"&gt;
&lt;tbody&gt;
&lt;tr style="height: 26.5px;"&gt;
&lt;td style="width: 22.7785%; height: 26.5px; text-align: center;"&gt;&lt;strong&gt;&lt;span style="font-family: georgia, palatino, serif;"&gt;Ítem de Observación&lt;/span&gt;&lt;/strong&gt;&lt;/td&gt;
&lt;td style="width: 18.1477%; height: 26.5px; text-align: center;"&gt;&lt;strong&gt;&lt;span style="font-family: georgia, palatino, serif;"&gt;Sí&lt;/span&gt;&lt;/strong&gt;&lt;/td&gt;
&lt;td style="width: 18.1477%; height: 26.5px; text-align: center;"&gt;&lt;strong&gt;&lt;span style="font-family: georgia, palatino, serif;"&gt;No&amp;nbsp;&lt;/span&gt;&lt;/strong&gt;&lt;/td&gt;
&lt;td style="width: 18.1477%; height: 26.5px; text-align: center;"&gt;&lt;strong&gt;&lt;span style="font-family: georgia, palatino, serif;"&gt;En proceso&amp;nbsp;&lt;/span&gt;&lt;/strong&gt;&lt;/td&gt;
&lt;td style="width: 22.7785%; height: 26.5px; text-align: center;"&gt;&lt;strong&gt;&lt;span style="font-family: georgia, palatino, serif;"&gt;Observaciones&lt;/span&gt;&lt;/strong&gt;&lt;/td&gt;
&lt;/tr&gt;
&lt;tr style="height: 17px;"&gt;
&lt;td style="width: 22.7785%; height: 17px; text-align: justify;"&gt;&lt;span style="font-family: georgia, palatino, serif;"&gt;Actitud y observación: Busco lugares y hago fotos&lt;/span&gt;&lt;/td&gt;
&lt;td style="width: 18.1477%; height: 17px;"&gt;&lt;br&gt;&lt;/td&gt;
&lt;td style="width: 18.1477%; height: 17px;"&gt;&lt;br&gt;&lt;/td&gt;
&lt;td style="width: 18.1477%; height: 17px;"&gt;&lt;br&gt;&lt;/td&gt;
&lt;td style="width: 22.7785%; height: 17px;"&gt;&lt;br&gt;&lt;/td&gt;
&lt;/tr&gt;
&lt;tr style="height: 26px;"&gt;
&lt;td style="width: 22.7785%; height: 26px; text-align: justify;"&gt;
&lt;p&gt;&lt;span style="font-family: georgia, palatino, serif;"&gt;Trabajo colaborativo: Ayuda a mi pareja.&amp;nbsp;&lt;/span&gt;&lt;/p&gt;
&lt;/td&gt;
&lt;td style="width: 18.1477%; height: 26px;"&gt;&lt;br&gt;&lt;/td&gt;
&lt;td style="width: 18.1477%; height: 26px;"&gt;&lt;br&gt;&lt;/td&gt;
&lt;td style="width: 18.1477%; height: 26px;"&gt;&lt;br&gt;&lt;/td&gt;
&lt;td style="width: 22.7785%; height: 26px;"&gt;&lt;br&gt;&lt;/td&gt;
&lt;/tr&gt;
&lt;tr style="height: 26px;"&gt;
&lt;td style="width: 22.7785%; height: 26px; text-align: justify;"&gt;&lt;span style="font-family: georgia, palatino, serif;"&gt;Ciudadanos de 10: Respetamos las normas de tráfico, el mobiliario y no tiramos basura.&lt;/span&gt;&lt;/td&gt;
&lt;td style="width: 18.1477%; height: 26px;"&gt;&lt;br&gt;&lt;/td&gt;
&lt;td style="width: 18.1477%; height: 26px;"&gt;&lt;br&gt;&lt;/td&gt;
&lt;td style="width: 18.1477%; height: 26px;"&gt;&lt;br&gt;&lt;/td&gt;
&lt;td style="width: 22.7785%; height: 26px;"&gt;&lt;br&gt;&lt;/td&gt;
&lt;/tr&gt;
&lt;tr style="height: 26.5px;"&gt;
&lt;td style="width: 22.7785%; height: 26.5px; text-align: justify;"&gt;&lt;span style="font-family: georgia, palatino, serif;"&gt;Competencia digital: Cuido la tablet y la cámara.&lt;/span&gt;&lt;/td&gt;
&lt;td style="width: 18.1477%; height: 26.5px;"&gt;&lt;br&gt;&lt;/td&gt;
&lt;td style="width: 18.1477%; height: 26.5px;"&gt;&lt;br&gt;&lt;/td&gt;
&lt;td style="width: 18.1477%; height: 26.5px;"&gt;&lt;br&gt;&lt;/td&gt;
&lt;td style="width: 22.7785%; height: 26.5px;"&gt;&lt;/td&gt;
&lt;/tr&gt;
&lt;/tbody&gt;
&lt;/table&gt;&lt;p class="clearfix"&gt;&lt;/p&gt;&lt;/div&gt;
            &lt;/div&gt;&lt;/div&gt;&lt;/div&gt;</htmlView><jsonProperties>{"ideviceId":"20260322193958270MZV","textInfoDurationInput":"","textInfoDurationTextInput":"Duración","textInfoParticipantsInput":"","textInfoParticipantsTextInput":"Agrupamiento","textTextarea":"&lt;p&gt;\"Hoja de Misión: Salida al Barrio\" (Checklist)&lt;/p&gt;\n&lt;p&gt;Chicos y chicas, mientras paseamos por el barrio, vuestra maestra llevará esta lista para ver qué bien trabajáis en equipo y cómo cuidáis vuestra tablet. ¡Seguro que todos conseguís muchos SÍ!\"&lt;br /&gt; &lt;/p&gt;\n&lt;table border=\"1\" class=\"exe-table\" style=\"width: 100%; height: 122px;\"&gt;\n&lt;tbody&gt;\n&lt;tr style=\"height: 26.5px;\"&gt;\n&lt;td style=\"width: 22.7785%; height: 26.5px; text-align: center;\"&gt;&lt;strong&gt;&lt;span style=\"font-family: georgia, palatino, serif;\"&gt;Ítem de Observación&lt;/span&gt;&lt;/strong&gt;&lt;/td&gt;\n&lt;td style=\"width: 18.1477%; height: 26.5px; text-align: center;\"&gt;&lt;strong&gt;&lt;span style=\"font-family: georgia, palatino, serif;\"&gt;Sí&lt;/span&gt;&lt;/strong&gt;&lt;/td&gt;\n&lt;td style=\"width: 18.1477%; height: 26.5px; text-align: center;\"&gt;&lt;strong&gt;&lt;span style=\"font-family: georgia, palatino, serif;\"&gt;No &lt;/span&gt;&lt;/strong&gt;&lt;/td&gt;\n&lt;td style=\"width: 18.1477%; height: 26.5px; text-align: center;\"&gt;&lt;strong&gt;&lt;span style=\"font-family: georgia, palatino, serif;\"&gt;En proceso &lt;/span&gt;&lt;/strong&gt;&lt;/td&gt;\n&lt;td style=\"width: 22.7785%; height: 26.5px; text-align: center;\"&gt;&lt;strong&gt;&lt;span style=\"font-family: georgia, palatino, serif;\"&gt;Observaciones&lt;/span&gt;&lt;/strong&gt;&lt;/td&gt;\n&lt;/tr&gt;\n&lt;tr style=\"height: 17px;\"&gt;\n&lt;td style=\"width: 22.7785%; height: 17px; text-align: justify;\"&gt;&lt;span style=\"font-family: georgia, palatino, serif;\"&gt;Actitud y observación: Busco lugares y hago fotos&lt;/span&gt;&lt;/td&gt;\n&lt;td style=\"width: 18.1477%; height: 17px;\"&gt;&lt;br /&gt;&lt;/td&gt;\n&lt;td style=\"width: 18.1477%; height: 17px;\"&gt;&lt;br /&gt;&lt;/td&gt;\n&lt;td style=\"width: 18.1477%; height: 17px;\"&gt;&lt;br /&gt;&lt;/td&gt;\n&lt;td style=\"width: 22.7785%; height: 17px;\"&gt;&lt;br /&gt;&lt;/td&gt;\n&lt;/tr&gt;\n&lt;tr style=\"height: 26px;\"&gt;\n&lt;td style=\"width: 22.7785%; height: 26px; text-align: justify;\"&gt;\n&lt;p&gt;&lt;span style=\"font-family: georgia, palatino, serif;\"&gt;Trabajo colaborativo: Ayuda a mi pareja. &lt;/span&gt;&lt;/p&gt;\n&lt;/td&gt;\n&lt;td style=\"width: 18.1477%; height: 26px;\"&gt;&lt;br /&gt;&lt;/td&gt;\n&lt;td style=\"width: 18.1477%; height: 26px;\"&gt;&lt;br /&gt;&lt;/td&gt;\n&lt;td style=\"width: 18.1477%; height: 26px;\"&gt;&lt;br /&gt;&lt;/td&gt;\n&lt;td style=\"width: 22.7785%; height: 26px;\"&gt;&lt;br /&gt;&lt;/td&gt;\n&lt;/tr&gt;\n&lt;tr style=\"height: 26px;\"&gt;\n&lt;td style=\"width: 22.7785%; height: 26px; text-align: justify;\"&gt;&lt;span style=\"font-family: georgia, palatino, serif;\"&gt;Ciudadanos de 10: Respetamos las normas de tráfico, el mobiliario y no tiramos basura.&lt;/span&gt;&lt;/td&gt;\n&lt;td style=\"width: 18.1477%; height: 26px;\"&gt;&lt;br /&gt;&lt;/td&gt;\n&lt;td style=\"width: 18.1477%; height: 26px;\"&gt;&lt;br /&gt;&lt;/td&gt;\n&lt;td style=\"width: 18.1477%; height: 26px;\"&gt;&lt;br /&gt;&lt;/td&gt;\n&lt;td style=\"width: 22.7785%; height: 26px;\"&gt;&lt;br /&gt;&lt;/td&gt;\n&lt;/tr&gt;\n&lt;tr style=\"height: 26.5px;\"&gt;\n&lt;td style=\"width: 22.7785%; height: 26.5px; text-align: justify;\"&gt;&lt;span style=\"font-family: georgia, palatino, serif;\"&gt;Competencia digital: Cuido la tablet y la cámara.&lt;/span&gt;&lt;/td&gt;\n&lt;td style=\"width: 18.1477%; height: 26.5px;\"&gt;&lt;br /&gt;&lt;/td&gt;\n&lt;td style=\"width: 18.1477%; height: 26.5px;\"&gt;&lt;br /&gt;&lt;/td&gt;\n&lt;td style=\"width: 18.1477%; height: 26.5px;\"&gt;&lt;br /&gt;&lt;/td&gt;\n&lt;td style=\"width: 22.7785%; height: 26.5px;\"&gt;&lt;/td&gt;\n&lt;/tr&gt;\n&lt;/tbody&gt;\n&lt;/table&gt;","textFeedbackInput":"Mostrar retroalimentación","textFeedbackTextarea":""}</jsonProperties><odeComponentsOrder>1</odeComponentsOrder><odeComponentsProperties><odeComponentsProperty><key>visibility</key><value>true</value></odeComponentsProperty><odeComponentsProperty><key>teacherOnly</key><value>false</value></odeComponentsProperty><odeComponentsProperty><key>identifier</key><value/></odeComponentsProperty><odeComponentsProperty><key>cssClass</key><value/></odeComponentsProperty></odeComponentsProperties></odeComponent></odeComponents></odePagStructure><odePagStructure><odePageId>20260322190753BBONLV</odePageId><odeBlockId>20260322190753PUADUI</odeBlockId><blockName>Nuestra rúbrica del mapa</blockName><iconName>observe</iconName><odePagStructureOrder>4</odePagStructureOrder><odePagStructureProperties><odePagStructureProperty><key>visibility</key><value>true</value></odePagStructureProperty><odePagStructureProperty><key>teacherOnly</key><value>false</value></odePagStructureProperty><odePagStructureProperty><key>allowToggle</key><value>true</value></odePagStructureProperty><odePagStructureProperty><key>minimized</key><value>false</value></odePagStructureProperty><odePagStructureProperty><key>identifier</key><value/></odePagStructureProperty><odePagStructureProperty><key>cssClass</key><value/></odePagStructureProperty></odePagStructureProperties><odeComponents><odeComponent><odePageId>20260322190753BBONLV</odePageId><odeBlockId>20260322190753PUADUI</odeBlockId><odeIdeviceId>202603221812033216VH</odeIdeviceId><odeIdeviceTypeName>text</odeIdeviceTypeName><htmlView>&lt;div class="exe-text-template"&gt;&lt;div class="textIdeviceContent"&gt;
            &lt;div class="exe-text-activity"&gt;
                &lt;div&gt;&lt;p style="text-align: center;"&gt;&lt;span style="font-family: georgia, palatino, serif;"&gt;&lt;strong&gt;&lt;span style="font-size: 14pt;"&gt;🌟 ¿Qué vamos a mirar en vuestro trabajo?&lt;/span&gt;&lt;/strong&gt;&lt;/span&gt;&lt;/p&gt;
&lt;p&gt;&lt;span style="font-family: georgia, palatino, serif;"&gt;Para que vuestro mapa sea de 10, vuestra maestra mirará:&lt;/span&gt;&lt;/p&gt;
&lt;ul&gt;
&lt;li style="text-align: justify;"&gt;&lt;span style="font-family: georgia, palatino, serif;"&gt;Si habéis sido respetuosos con los vecinos (Criterio 5.3.b).&lt;/span&gt;&lt;/li&gt;
&lt;li style="text-align: justify;"&gt;&lt;span style="font-family: georgia, palatino, serif;"&gt;Si usáis la tablet con cuidado y seguridad (Criterio 1.1.b).&lt;/span&gt;&lt;/li&gt;
&lt;li style="text-align: justify;"&gt;&lt;span style="font-family: georgia, palatino, serif;"&gt;Si vuestro dibujo y audio ayudan a conocer el barrio (Criterio 4.1.b).&lt;/span&gt;&lt;/li&gt;
&lt;/ul&gt;
&lt;table border="1" class="exe-table" style="width: 100%; height: 1540.5px;"&gt;
&lt;tbody&gt;
&lt;tr style="height: 50.5px;"&gt;
&lt;td style="width: 49.8058%; height: 50.5px; text-align: center;"&gt;&lt;strong&gt;&lt;span style="font-family: georgia, palatino, serif;"&gt;Tarea&amp;nbsp;&lt;/span&gt;&lt;/strong&gt;&lt;/td&gt;
&lt;td style="width: 50.1942%; height: 50.5px; text-align: center;"&gt;&lt;strong&gt;&lt;span style="font-family: georgia, palatino, serif;"&gt;Criterio de evaluación&lt;/span&gt;&lt;/strong&gt;&lt;/td&gt;
&lt;/tr&gt;
&lt;tr style="height: 153px;"&gt;
&lt;td style="width: 49.8058%; height: 153px; text-align: justify;"&gt;
&lt;p&gt;&lt;span style="font-family: georgia, palatino, serif;"&gt;1. Presentación de la actividad y reflexión sobre el barrio: el alumnado comenta qué lugares conoce y cuáles consideran importantes.&lt;/span&gt;&lt;/p&gt;
&lt;/td&gt;
&lt;td style="width: 50.1942%; height: 153px; text-align: justify;"&gt;
&lt;p&gt;&lt;span style="font-family: georgia, palatino, serif;"&gt;2.1.b. Mostrar curiosidad por objetos, hechos y fenómenos cercanos, formulando preguntas y realizando predicciones.&lt;/span&gt;&lt;/p&gt;
&lt;/td&gt;
&lt;/tr&gt;
&lt;tr style="height: 201px;"&gt;
&lt;td style="width: 49.8058%; height: 201px; text-align: justify;"&gt;&lt;span style="font-family: georgia, palatino, serif;"&gt;2. Salida al barrio: identificar y fotografiar puntos clave (ayuntamiento, parque, biblioteca, comercios)&lt;/span&gt;&lt;br&gt;&lt;/td&gt;
&lt;td style="width: 50.1942%; height: 201px; text-align: justify;"&gt;
&lt;p&gt;&lt;span style="font-family: georgia, palatino, serif;"&gt;5.3.b. Mostrar actitudes de respeto para el disfrute del patrimonio natural y cultural, reconociéndolo como un bien común y adoptando conductas respetuosas para su disfrute.&lt;/span&gt;&lt;/p&gt;
&lt;/td&gt;
&lt;/tr&gt;
&lt;tr style="height: 225px;"&gt;
&lt;td style="width: 49.8058%; height: 225px; text-align: justify;"&gt;&lt;span style="font-family: georgia, palatino, serif;"&gt;&amp;nbsp;3. Elaboración de dibujos del lugar visitado, integrando elementos observados.&lt;/span&gt;&lt;br&gt;&lt;/td&gt;
&lt;td style="width: 50.1942%; height: 225px; text-align: justify;"&gt;
&lt;p&gt;&lt;span style="font-family: georgia, palatino, serif;"&gt;4.1.b. Participar de manera guiada en el diseño de producciones culturales y artísticas elementales, trabajando de forma cooperativa a partir de la igualdad y el respeto a la diversidad.&lt;/span&gt;&lt;/p&gt;
&lt;/td&gt;
&lt;/tr&gt;
&lt;tr style="height: 153px;"&gt;
&lt;td style="width: 49.8058%; height: 153px; text-align: justify;"&gt;&lt;span style="font-family: georgia, palatino, serif;"&gt;4. Grabación de audio explicativo: cada alumno comenta por qué ese lugar es importante y cómo cuidarlo&lt;/span&gt;&lt;/td&gt;
&lt;td style="width: 50.1942%; height: 153px; text-align: justify;"&gt;
&lt;p&gt;&lt;span style="font-family: georgia, palatino, serif;"&gt;1.1.b. Utilizar dispositivos y recursos digitales de acuerdo con las necesidades del contexto educativo de forma segura.&lt;/span&gt;&lt;/p&gt;
&lt;/td&gt;
&lt;/tr&gt;
&lt;tr style="height: 153px;"&gt;
&lt;td style="width: 49.8058%; height: 153px; text-align: justify;"&gt;
&lt;p&gt;&lt;span style="font-family: georgia, palatino, serif;"&gt;5. Escaneo o digitalización de los dibujos realizados en clase.&lt;/span&gt;&lt;/p&gt;
&lt;/td&gt;
&lt;td style="width: 50.1942%; height: 153px; text-align: justify;"&gt;
&lt;p&gt;&lt;span style="font-family: georgia, palatino, serif;"&gt;1.1.b. Utilizar dispositivos y recursos digitales de acuerdo con las necesidades del contexto educativo de forma segura.&lt;/span&gt;&lt;/p&gt;
&lt;/td&gt;
&lt;/tr&gt;
&lt;tr style="height: 201px;"&gt;
&lt;td style="width: 49.8058%; height: 201px; text-align: justify;"&gt;&lt;span style="font-family: georgia, palatino, serif;"&gt;6. Integración de fotos, dibujos y audios en Genially para crear el Mapa Interactivo Digital del Barrio.&lt;/span&gt;&lt;/td&gt;
&lt;td style="width: 50.1942%; height: 201px; text-align: justify;"&gt;
&lt;p&gt;&lt;span style="font-family: georgia, palatino, serif;"&gt;2.2.b. Buscar información sencilla de diferentes fuentes seguras y fiables de forma guiada, utilizándola en investigaciones relacionadas con el medio natural, social y cultural.&lt;/span&gt;&lt;/p&gt;
&lt;/td&gt;
&lt;/tr&gt;
&lt;tr style="height: 225px;"&gt;
&lt;td style="width: 49.8058%; height: 225px; text-align: justify;"&gt;&lt;span style="font-family: georgia, palatino, serif;"&gt;7. Presentación del mapa digital al grupo y discusión sobre normas de convivencia y cuidado del barrio.&lt;/span&gt;&lt;/td&gt;
&lt;td style="width: 50.1942%; height: 225px; text-align: justify;"&gt;
&lt;p&gt;&lt;span style="font-family: georgia, palatino, serif;"&gt;3.1.b. Realizar, de forma guiada, un producto final sencillo que dé solución a un problema de diseño, probando en equipo diferentes prototipos y utilizando de forma segura los materiales adecuados.&lt;/span&gt;&lt;/p&gt;
&lt;/td&gt;
&lt;/tr&gt;
&lt;tr style="height: 179px;"&gt;
&lt;td style="width: 49.8058%; height: 179px; text-align: justify;"&gt;&lt;span style="font-family: georgia, palatino, serif;"&gt;8. Evaluación del producto final: cada alumno revisa si se respetó la imagen digital y realiza autoevaluación&lt;/span&gt;&lt;/td&gt;
&lt;td style="width: 50.1942%; height: 179px; text-align: justify;"&gt;
&lt;p&gt;&lt;span style="font-family: georgia, palatino, serif;"&gt;5.3.b. Mostrar actitudes de respeto para el disfrute del patrimonio natural y cultural, reconociéndolo como un bien común y&amp;nbsp; adoptando conductas respetuosas para su disfrute.&amp;nbsp;&lt;/span&gt;&lt;/p&gt;
&lt;/td&gt;
&lt;/tr&gt;
&lt;/tbody&gt;
&lt;/table&gt;&lt;p class="clearfix"&gt;&lt;/p&gt;&lt;/div&gt;
            &lt;/div&gt;&lt;/div&gt;&lt;/div&gt;</htmlView><jsonProperties>{"ideviceId":"202603221812033216VH","textInfoDurationInput":"","textInfoDurationTextInput":"Duración","textInfoParticipantsInput":"","textInfoParticipantsTextInput":"Agrupamiento","textTextarea":"&lt;p style=\"text-align: center;\"&gt;&lt;span style=\"font-family: georgia, palatino, serif;\"&gt;&lt;strong&gt;&lt;span style=\"font-size: 14pt;\"&gt;🌟 ¿Qué vamos a mirar en vuestro trabajo?&lt;/span&gt;&lt;/strong&gt;&lt;/span&gt;&lt;/p&gt;\n&lt;p&gt;&lt;span style=\"font-family: georgia, palatino, serif;\"&gt;Para que vuestro mapa sea de 10, vuestra maestra mirará:&lt;/span&gt;&lt;/p&gt;\n&lt;ul&gt;\n&lt;li style=\"text-align: justify;\"&gt;&lt;span style=\"font-family: georgia, palatino, serif;\"&gt;Si habéis sido respetuosos con los vecinos (Criterio 5.3.b).&lt;/span&gt;&lt;/li&gt;\n&lt;li style=\"text-align: justify;\"&gt;&lt;span style=\"font-family: georgia, palatino, serif;\"&gt;Si usáis la tablet con cuidado y seguridad (Criterio 1.1.b).&lt;/span&gt;&lt;/li&gt;\n&lt;li style=\"text-align: justify;\"&gt;&lt;span style=\"font-family: georgia, palatino, serif;\"&gt;Si vuestro dibujo y audio ayudan a conocer el barrio (Criterio 4.1.b).&lt;/span&gt;&lt;/li&gt;\n&lt;/ul&gt;\n&lt;table border=\"1\" class=\"exe-table\" style=\"width: 100%; height: 1540.5px;\"&gt;\n&lt;tbody&gt;\n&lt;tr style=\"height: 50.5px;\"&gt;\n&lt;td style=\"width: 49.8058%; height: 50.5px; text-align: center;\"&gt;&lt;strong&gt;&lt;span style=\"font-family: georgia, palatino, serif;\"&gt;Tarea &lt;/span&gt;&lt;/strong&gt;&lt;/td&gt;\n&lt;td style=\"width: 50.1942%; height: 50.5px; text-align: center;\"&gt;&lt;strong&gt;&lt;span style=\"font-family: georgia, palatino, serif;\"&gt;Criterio de evaluación&lt;/span&gt;&lt;/strong&gt;&lt;/td&gt;\n&lt;/tr&gt;\n&lt;tr style=\"height: 153px;\"&gt;\n&lt;td style=\"width: 49.8058%; height: 153px; text-align: justify;\"&gt;\n&lt;p&gt;&lt;span style=\"font-family: georgia, palatino, serif;\"&gt;1. Presentación de la actividad y reflexión sobre el barrio: el alumnado comenta qué lugares conoce y cuáles consideran importantes.&lt;/span&gt;&lt;/p&gt;\n&lt;/td&gt;\n&lt;td style=\"width: 50.1942%; height: 153px; text-align: justify;\"&gt;\n&lt;p&gt;&lt;span style=\"font-family: georgia, palatino, serif;\"&gt;2.1.b. Mostrar curiosidad por objetos, hechos y fenómenos cercanos, formulando preguntas y realizando predicciones.&lt;/span&gt;&lt;/p&gt;\n&lt;/td&gt;\n&lt;/tr&gt;\n&lt;tr style=\"height: 201px;\"&gt;\n&lt;td style=\"width: 49.8058%; height: 201px; text-align: justify;\"&gt;&lt;span style=\"font-family: georgia, palatino, serif;\"&gt;2. Salida al barrio: identificar y fotografiar puntos clave (ayuntamiento, parque, biblioteca, comercios)&lt;/span&gt;&lt;br /&gt;&lt;/td&gt;\n&lt;td style=\"width: 50.1942%; height: 201px; text-align: justify;\"&gt;\n&lt;p&gt;&lt;span style=\"font-family: georgia, palatino, serif;\"&gt;5.3.b. Mostrar actitudes de respeto para el disfrute del patrimonio natural y cultural, reconociéndolo como un bien común y adoptando conductas respetuosas para su disfrute.&lt;/span&gt;&lt;/p&gt;\n&lt;/td&gt;\n&lt;/tr&gt;\n&lt;tr style=\"height: 225px;\"&gt;\n&lt;td style=\"width: 49.8058%; height: 225px; text-align: justify;\"&gt;&lt;span style=\"font-family: georgia, palatino, serif;\"&gt; 3. Elaboración de dibujos del lugar visitado, integrando elementos observados.&lt;/span&gt;&lt;br /&gt;&lt;/td&gt;\n&lt;td style=\"width: 50.1942%; height: 225px; text-align: justify;\"&gt;\n&lt;p&gt;&lt;span style=\"font-family: georgia, palatino, serif;\"&gt;4.1.b. Participar de manera guiada en el diseño de producciones culturales y artísticas elementales, trabajando de forma cooperativa a partir de la igualdad y el respeto a la diversidad.&lt;/span&gt;&lt;/p&gt;\n&lt;/td&gt;\n&lt;/tr&gt;\n&lt;tr style=\"height: 153px;\"&gt;\n&lt;td style=\"width: 49.8058%; height: 153px; text-align: justify;\"&gt;&lt;span style=\"font-family: georgia, palatino, serif;\"&gt;4. Grabación de audio explicativo: cada alumno comenta por qué ese lugar es importante y cómo cuidarlo&lt;/span&gt;&lt;/td&gt;\n&lt;td style=\"width: 50.1942%; height: 153px; text-align: justify;\"&gt;\n&lt;p&gt;&lt;span style=\"font-family: georgia, palatino, serif;\"&gt;1.1.b. Utilizar dispositivos y recursos digitales de acuerdo con las necesidades del contexto educativo de forma segura.&lt;/span&gt;&lt;/p&gt;\n&lt;/td&gt;\n&lt;/tr&gt;\n&lt;tr style=\"height: 153px;\"&gt;\n&lt;td style=\"width: 49.8058%; height: 153px; text-align: justify;\"&gt;\n&lt;p&gt;&lt;span style=\"font-family: georgia, palatino, serif;\"&gt;5. Escaneo o digitalización de los dibujos realizados en clase.&lt;/span&gt;&lt;/p&gt;\n&lt;/td&gt;\n&lt;td style=\"width: 50.1942%; height: 153px; text-align: justify;\"&gt;\n&lt;p&gt;&lt;span style=\"font-family: georgia, palatino, serif;\"&gt;1.1.b. Utilizar dispositivos y recursos digitales de acuerdo con las necesidades del contexto educativo de forma segura.&lt;/span&gt;&lt;/p&gt;\n&lt;/td&gt;\n&lt;/tr&gt;\n&lt;tr style=\"height: 201px;\"&gt;\n&lt;td style=\"width: 49.8058%; height: 201px; text-align: justify;\"&gt;&lt;span style=\"font-family: georgia, palatino, serif;\"&gt;6. Integración de fotos, dibujos y audios en Genially para crear el Mapa Interactivo Digital del Barrio.&lt;/span&gt;&lt;/td&gt;\n&lt;td style=\"width: 50.1942%; height: 201px; text-align: justify;\"&gt;\n&lt;p&gt;&lt;span style=\"font-family: georgia, palatino, serif;\"&gt;2.2.b. Buscar información sencilla de diferentes fuentes seguras y fiables de forma guiada, utilizándola en investigaciones relacionadas con el medio natural, social y cultural.&lt;/span&gt;&lt;/p&gt;\n&lt;/td&gt;\n&lt;/tr&gt;\n&lt;tr style=\"height: 225px;\"&gt;\n&lt;td style=\"width: 49.8058%; height: 225px; text-align: justify;\"&gt;&lt;span style=\"font-family: georgia, palatino, serif;\"&gt;7. Presentación del mapa digital al grupo y discusión sobre normas de convivencia y cuidado del barrio.&lt;/span&gt;&lt;/td&gt;\n&lt;td style=\"width: 50.1942%; height: 225px; text-align: justify;\"&gt;\n&lt;p&gt;&lt;span style=\"font-family: georgia, palatino, serif;\"&gt;3.1.b. Realizar, de forma guiada, un producto final sencillo que dé solución a un problema de diseño, probando en equipo diferentes prototipos y utilizando de forma segura los materiales adecuados.&lt;/span&gt;&lt;/p&gt;\n&lt;/td&gt;\n&lt;/tr&gt;\n&lt;tr style=\"height: 179px;\"&gt;\n&lt;td style=\"width: 49.8058%; height: 179px; text-align: justify;\"&gt;&lt;span style=\"font-family: georgia, palatino, serif;\"&gt;8. Evaluación del producto final: cada alumno revisa si se respetó la imagen digital y realiza autoevaluación&lt;/span&gt;&lt;/td&gt;\n&lt;td style=\"width: 50.1942%; height: 179px; text-align: justify;\"&gt;\n&lt;p&gt;&lt;span style=\"font-family: georgia, palatino, serif;\"&gt;5.3.b. Mostrar actitudes de respeto para el disfrute del patrimonio natural y cultural, reconociéndolo como un bien común y  adoptando conductas respetuosas para su disfrute. &lt;/span&gt;&lt;/p&gt;\n&lt;/td&gt;\n&lt;/tr&gt;\n&lt;/tbody&gt;\n&lt;/table&gt;","textFeedbackInput":"Mostrar retroalimentación","textFeedbackTextarea":""}</jsonProperties><odeComponentsOrder>1</odeComponentsOrder><odeComponentsProperties><odeComponentsProperty><key>visibility</key><value>true</value></odeComponentsProperty><odeComponentsProperty><key>teacherOnly</key><value>false</value></odeComponentsProperty><odeComponentsProperty><key>identifier</key><value/></odeComponentsProperty><odeComponentsProperty><key>cssClass</key><value/></odeComponentsProperty></odeComponentsProperties></odeComponent></odeComponents></odePagStructure></odePagStructures></odeNavStructure><odeNavStructure><odePageId>20260322190753ERDSNC</odePageId><odeParentPageId>20260322190753ENIYTU</odeParentPageId><pageName>Créditos </pageName><odeNavStructureOrder>6</odeNavStructureOrder><odeNavStructureProperties><odeNavStructureProperty><key>titleNode</key><value/></odeNavStructureProperty><odeNavStructureProperty><key>hidePageTitle</key><value>false</value></odeNavStructureProperty><odeNavStructureProperty><key>titleHtml</key><value/></odeNavStructureProperty><odeNavStructureProperty><key>editableInPage</key><value>false</value></odeNavStructureProperty><odeNavStructureProperty><key>titlePage</key><value>Créditos </value></odeNavStructureProperty><odeNavStructureProperty><key>visibility</key><value>true</value></odeNavStructureProperty><odeNavStructureProperty><key>highlight</key><value>false</value></odeNavStructureProperty><odeNavStructureProperty><key>description</key><value/></odeNavStructureProperty></odeNavStructureProperties><odePagStructures><odePagStructure><odePageId>20260322190753ERDSNC</odePageId><odeBlockId>20260322190753GFNDHF</odeBlockId><blockName>Texto</blockName><iconName/><odePagStructureOrder>1</odePagStructureOrder><odePagStructureProperties><odePagStructureProperty><key>visibility</key><value>true</value></odePagStructureProperty><odePagStructureProperty><key>teacherOnly</key><value>false</value></odePagStructureProperty><odePagStructureProperty><key>allowToggle</key><value>true</value></odePagStructureProperty><odePagStructureProperty><key>minimized</key><value>false</value></odePagStructureProperty><odePagStructureProperty><key>identifier</key><value/></odePagStructureProperty><odePagStructureProperty><key>cssClass</key><value/></odePagStructureProperty></odePagStructureProperties><odeComponents><odeComponent><odePageId>20260322190753ERDSNC</odePageId><odeBlockId>20260322190753GFNDHF</odeBlockId><odeIdeviceId>202603222001045890C5</odeIdeviceId><odeIdeviceTypeName>text</odeIdeviceTypeName><htmlView>&lt;div class="exe-text-template"&gt;&lt;div class="textIdeviceContent"&gt;
            &lt;div class="exe-text-activity"&gt;
                &lt;div&gt;&lt;p style="text-align: justify;"&gt;&lt;strong&gt;&lt;span style="font-family: georgia, palatino, serif;"&gt;Autoría:&lt;/span&gt;&lt;/strong&gt;&lt;/p&gt;
&lt;p style="text-align: justify;"&gt;&lt;span style="font-family: georgia, palatino, serif;"&gt;Este Recurso Educativo Abierto ha sido creado por Araceli Servián Cordón para el curso de Competencia Digital Docente (Nivel B2).&lt;/span&gt;&lt;/p&gt;
&lt;p style="text-align: justify;"&gt;&lt;span style="font-family: georgia, palatino, serif;"&gt;Haz clic aquí para descargar el archivo editable (.elp) de este proyecto: &lt;a href="{{context_path}}/202603222001045890C5/Mi_barrio_en_360_web.zip" title="Mi_barrio_en_360_web.zip" size="1.11 MB" id="link_0"&gt;{{context_path}}/202603222001045890C5/Mi_barrio_en_360_web.zip&lt;/a&gt;&lt;/span&gt;&lt;/p&gt;
&lt;p style="text-align: justify;"&gt;&lt;span style="font-family: georgia, palatino, serif;"&gt;Licencia: Este material se publica bajo una licencia Creative Commons Reconocimiento-NoComercial-CompartirIgual 4.0 (CC BY-NC-SA).&amp;nbsp;&lt;/span&gt;&lt;/p&gt;
&lt;p style="text-align: justify;"&gt;&lt;span style="font-family: georgia, palatino, serif;"&gt;Agradecimientos y Fuentes: Para la elaboración de este recurso se han utilizado contenidos y herramientas de:&lt;/span&gt;&lt;/p&gt;
&lt;ul&gt;
&lt;li style="text-align: justify;"&gt;&lt;span style="font-family: georgia, palatino, serif;"&gt;Junta de Andalucía: Imágenes y orientaciones pedagógicas (Materiales REA).&lt;/span&gt;&lt;/li&gt;
&lt;li style="text-align: justify;"&gt;&lt;span style="font-family: georgia, palatino, serif;"&gt;Canva: Infografía de Protección de Datos (Tarea 2.3).&lt;/span&gt;&lt;/li&gt;
&lt;li style="text-align: justify;"&gt;&lt;span style="font-family: georgia, palatino, serif;"&gt;Genially: Mapa Interactivo del Barrio (Tarea 4.1).&lt;/span&gt;&lt;/li&gt;
&lt;li style="text-align: justify;"&gt;&lt;span style="font-family: georgia, palatino, serif;"&gt;Symbaloo y Padlet: Herramientas de curación de contenidos (Tarea 5.1).&lt;/span&gt;&lt;/li&gt;
&lt;/ul&gt;&lt;p class="clearfix"&gt;&lt;/p&gt;&lt;/div&gt;
            &lt;/div&gt;&lt;/div&gt;&lt;/div&gt;</htmlView><jsonProperties>{"ideviceId":"202603222001045890C5","textInfoDurationInput":"","textInfoDurationTextInput":"Duración","textInfoParticipantsInput":"","textInfoParticipantsTextInput":"Agrupamiento","textTextarea":"&lt;p style=\"text-align: justify;\"&gt;&lt;strong&gt;&lt;span style=\"font-family: georgia, palatino, serif;\"&gt;Autoría:&lt;/span&gt;&lt;/strong&gt;&lt;/p&gt;\n&lt;p style=\"text-align: justify;\"&gt;&lt;span style=\"font-family: georgia, palatino, serif;\"&gt;Este Recurso Educativo Abierto ha sido creado por Araceli Servián Cordón para el curso de Competencia Digital Docente (Nivel B2).&lt;/span&gt;&lt;/p&gt;\n&lt;p style=\"text-align: justify;\"&gt;&lt;span style=\"font-family: georgia, palatino, serif;\"&gt;Haz clic aquí para descargar el archivo editable (.elp) de este proyecto: &lt;a href=\"{{context_path}}/202603222001045890C5/Mi_barrio_en_360_web.zip\" title=\"Mi_barrio_en_360_web.zip\" size=\"1.11 MB\" id=\"link_0\"&gt;{{context_path}}/202603222001045890C5/Mi_barrio_en_360_web.zip&lt;/a&gt;&lt;/span&gt;&lt;/p&gt;\n&lt;p style=\"text-align: justify;\"&gt;&lt;span style=\"font-family: georgia, palatino, serif;\"&gt;Licencia: Este material se publica bajo una licencia Creative Commons Reconocimiento-NoComercial-CompartirIgual 4.0 (CC BY-NC-SA). &lt;/span&gt;&lt;/p&gt;\n&lt;p style=\"text-align: justify;\"&gt;&lt;span style=\"font-family: georgia, palatino, serif;\"&gt;Agradecimientos y Fuentes: Para la elaboración de este recurso se han utilizado contenidos y herramientas de:&lt;/span&gt;&lt;/p&gt;\n&lt;ul&gt;\n&lt;li style=\"text-align: justify;\"&gt;&lt;span style=\"font-family: georgia, palatino, serif;\"&gt;Junta de Andalucía: Imágenes y orientaciones pedagógicas (Materiales REA).&lt;/span&gt;&lt;/li&gt;\n&lt;li style=\"text-align: justify;\"&gt;&lt;span style=\"font-family: georgia, palatino, serif;\"&gt;Canva: Infografía de Protección de Datos (Tarea 2.3).&lt;/span&gt;&lt;/li&gt;\n&lt;li style=\"text-align: justify;\"&gt;&lt;span style=\"font-family: georgia, palatino, serif;\"&gt;Genially: Mapa Interactivo del Barrio (Tarea 4.1).&lt;/span&gt;&lt;/li&gt;\n&lt;li style=\"text-align: justify;\"&gt;&lt;span style=\"font-family: georgia, palatino, serif;\"&gt;Symbaloo y Padlet: Herramientas de curación de contenidos (Tarea 5.1).&lt;/span&gt;&lt;/li&gt;\n&lt;/ul&gt;","textFeedbackInput":"Mostrar retroalimentación","textFeedbackTextarea":""}</jsonProperties><odeComponentsOrder>1</odeComponentsOrder><odeComponentsProperties><odeComponentsProperty><key>visibility</key><value>true</value></odeComponentsProperty><odeComponentsProperty><key>teacherOnly</key><value>false</value></odeComponentsProperty><odeComponentsProperty><key>identifier</key><value/></odeComponentsProperty><odeComponentsProperty><key>cssClass</key><value/></odeComponentsProperty></odeComponentsProperties></odeComponent></odeComponents></odePagStructure></odePagStructures></odeNavStructure><odeNavStructure><odePageId>20260322190753OMCYDM</odePageId><odeParentPageId>20260322190753DHLJKB</odeParentPageId><pageName>Ficha técnica del producto (solo maestros/as)</pageName><odeNavStructureOrder>1</odeNavStructureOrder><odeNavStructureProperties><odeNavStructureProperty><key>titleNode</key><value/></odeNavStructureProperty><odeNavStructureProperty><key>hidePageTitle</key><value>false</value></odeNavStructureProperty><odeNavStructureProperty><key>titleHtml</key><value/></odeNavStructureProperty><odeNavStructureProperty><key>editableInPage</key><value>false</value></odeNavStructureProperty><odeNavStructureProperty><key>titlePage</key><value>Ficha técnica del producto (solo maestros/as)</value></odeNavStructureProperty><odeNavStructureProperty><key>visibility</key><value>true</value></odeNavStructureProperty><odeNavStructureProperty><key>highlight</key><value>false</value></odeNavStructureProperty><odeNavStructureProperty><key>description</key><value/></odeNavStructureProperty></odeNavStructureProperties><odePagStructures><odePagStructure><odePageId>20260322190753OMCYDM</odePageId><odeBlockId>20260322190753IOWLRD</odeBlockId><blockName>Ficha técnica</blockName><iconName/><odePagStructureOrder>1</odePagStructureOrder><odePagStructureProperties><odePagStructureProperty><key>visibility</key><value>true</value></odePagStructureProperty><odePagStructureProperty><key>teacherOnly</key><value>false</value></odePagStructureProperty><odePagStructureProperty><key>allowToggle</key><value>true</value></odePagStructureProperty><odePagStructureProperty><key>minimized</key><value>false</value></odePagStructureProperty><odePagStructureProperty><key>identifier</key><value/></odePagStructureProperty><odePagStructureProperty><key>cssClass</key><value/></odePagStructureProperty></odePagStructureProperties><odeComponents><odeComponent><odePageId>20260322190753OMCYDM</odePageId><odeBlockId>20260322190753IOWLRD</odeBlockId><odeIdeviceId>20260322163640385MS3</odeIdeviceId><odeIdeviceTypeName>text</odeIdeviceTypeName><htmlView>&lt;div class="exe-text-template"&gt;&lt;div class="textIdeviceContent"&gt;
            &lt;div class="exe-text-activity"&gt;
                &lt;div&gt;&lt;p style="text-align: justify;"&gt;&lt;span style="font-family: georgia, palatino, serif;"&gt;&lt;strong&gt;Objetivo de uso&lt;/strong&gt;: Crear un mapa interactivo digital del barrio donde el alumnado pueda incluir sus dibujos, fotos y audios explicativos de los lugares importantes de su entorno cercano.&lt;/span&gt;&lt;/p&gt;
&lt;p style="text-align: justify;"&gt;&lt;strong&gt;&lt;span style="font-family: georgia, palatino, serif;"&gt;Justificación de la elección de Genially:&lt;/span&gt;&lt;/strong&gt;&lt;br&gt;&lt;/p&gt;
&lt;ul&gt;
&lt;li style="text-align: justify;"&gt;&lt;span style="font-family: georgia, palatino, serif;"&gt;Versatilidad y accesibilidad: Permite combinar imágenes, audio, texto y animaciones en un mismo soporte. Los niños de 2º de Primaria pueden interactuar con él fácilmente, pulsando en los distintos elementos para escuchar sus grabaciones o ver sus dibujos. Además, el centro cuenta con dispositivos y conexión necesarios para su uso.&lt;/span&gt;&lt;/li&gt;
&lt;li style="text-align: justify;"&gt;&lt;span style="font-family: georgia, palatino, serif;"&gt;Adecuación al alumnado: A esta edad, los alumnos tienen competencias digitales iniciales, y Genially es intuitivo y visual, favoreciendo la autonomía con el apoyo del "Andamiaje por Parejas". La herramienta permite que los errores sean fáciles de corregir, ayudando a la gestión de la frustración ante fallos técnicos.&lt;/span&gt;&lt;/li&gt;
&lt;li style="text-align: justify;"&gt;&lt;span style="font-family: georgia, palatino, serif;"&gt;Contexto educativo y curricular: La actividad integra varias materias: Conocimiento del Medio (conocimiento del entorno), Lengua Castellana (expresión oral y escrita en los audios) y Educación Artística (dibujo y diseño digital). Genially facilita un aprendizaje transversal donde cada alumno puede expresarse y publicar su trabajo de manera segura y respetuosa con la imagen digital.&lt;/span&gt;&lt;/li&gt;
&lt;li style="text-align: justify;"&gt;&lt;span style="font-family: georgia, palatino, serif;"&gt;Producción de contenido digital: Esta herramienta transforma la actividad en una experiencia de aprendizaje activo y creativo, donde los alumnos se convierten en productores de contenido y no solo en consumidores. Les permite ver su propio trabajo de manera tangible y compartirlo con la comunidad educativa de forma segura.&lt;/span&gt;&lt;/li&gt;
&lt;/ul&gt;&lt;p class="clearfix"&gt;&lt;/p&gt;&lt;/div&gt;
            &lt;/div&gt;&lt;/div&gt;&lt;/div&gt;</htmlView><jsonProperties>{"ideviceId":"20260322163640385MS3","textInfoDurationInput":"","textInfoDurationTextInput":"Duración","textInfoParticipantsInput":"","textInfoParticipantsTextInput":"Agrupamiento","textTextarea":"&lt;p style=\"text-align: justify;\"&gt;&lt;span style=\"font-family: georgia, palatino, serif;\"&gt;&lt;strong&gt;Objetivo de uso&lt;/strong&gt;: Crear un mapa interactivo digital del barrio donde el alumnado pueda incluir sus dibujos, fotos y audios explicativos de los lugares importantes de su entorno cercano.&lt;/span&gt;&lt;/p&gt;\n&lt;p style=\"text-align: justify;\"&gt;&lt;strong&gt;&lt;span style=\"font-family: georgia, palatino, serif;\"&gt;Justificación de la elección de Genially:&lt;/span&gt;&lt;/strong&gt;&lt;br /&gt;&lt;/p&gt;\n&lt;ul&gt;\n&lt;li style=\"text-align: justify;\"&gt;&lt;span style=\"font-family: georgia, palatino, serif;\"&gt;Versatilidad y accesibilidad: Permite combinar imágenes, audio, texto y animaciones en un mismo soporte. Los niños de 2º de Primaria pueden interactuar con él fácilmente, pulsando en los distintos elementos para escuchar sus grabaciones o ver sus dibujos. Además, el centro cuenta con dispositivos y conexión necesarios para su uso.&lt;/span&gt;&lt;/li&gt;\n&lt;li style=\"text-align: justify;\"&gt;&lt;span style=\"font-family: georgia, palatino, serif;\"&gt;Adecuación al alumnado: A esta edad, los alumnos tienen competencias digitales iniciales, y Genially es intuitivo y visual, favoreciendo la autonomía con el apoyo del \"Andamiaje por Parejas\". La herramienta permite que los errores sean fáciles de corregir, ayudando a la gestión de la frustración ante fallos técnicos.&lt;/span&gt;&lt;/li&gt;\n&lt;li style=\"text-align: justify;\"&gt;&lt;span style=\"font-family: georgia, palatino, serif;\"&gt;Contexto educativo y curricular: La actividad integra varias materias: Conocimiento del Medio (conocimiento del entorno), Lengua Castellana (expresión oral y escrita en los audios) y Educación Artística (dibujo y diseño digital). Genially facilita un aprendizaje transversal donde cada alumno puede expresarse y publicar su trabajo de manera segura y respetuosa con la imagen digital.&lt;/span&gt;&lt;/li&gt;\n&lt;li style=\"text-align: justify;\"&gt;&lt;span style=\"font-family: georgia, palatino, serif;\"&gt;Producción de contenido digital: Esta herramienta transforma la actividad en una experiencia de aprendizaje activo y creativo, donde los alumnos se convierten en productores de contenido y no solo en consumidores. Les permite ver su propio trabajo de manera tangible y compartirlo con la comunidad educativa de forma segura.&lt;/span&gt;&lt;/li&gt;\n&lt;/ul&gt;","textFeedbackInput":"Mostrar retroalimentación","textFeedbackTextarea":""}</jsonProperties><odeComponentsOrder>1</odeComponentsOrder><odeComponentsProperties><odeComponentsProperty><key>visibility</key><value>true</value></odeComponentsProperty><odeComponentsProperty><key>teacherOnly</key><value>false</value></odeComponentsProperty><odeComponentsProperty><key>identifier</key><value/></odeComponentsProperty><odeComponentsProperty><key>cssClass</key><value/></odeComponentsProperty></odeComponentsProperties></odeComponent></odeComponents></odePagStructure></odePagStructures></odeNavStructure></odeNavStructures></ode>
